Workbook

Sheet Mapping
A1: SLFTTP | B1: Orea Transaction.TransactionType | C1: SLFLNT
A2: 01 | B2: "SALE" => "01", if there is no employee discount i.e., When SLFPVC is not EMP | C2: 01 | D2: If Customer ID doesnot exists and if SLFTTP is 01 / Sale | E2: REGULAR SALES
A3: 01 | B3: "SALE" => "01", if there is no employee discount i.e., When SLFPVC is not EMP | C3: 02 | D3: If Customer ID exists and if SLFTTP is 01 / Sale | E3: REGULAR TRADE
A4: 01 | C4: 43 | D4: "AR_PAYMENT" => "43", | E4: AR PAYMENT
A5: 01 | B5: "SALE" => "01", if there is no employee discount i.e., When SLFPVC is not EMP | C5: 45 | D5: If Tenders.Method = "GIFTCARD" | E5: GIFT CARD SALES
A6: 04 | B6: "SALE" => "04", if there is employee discount i.e., When PVCode is EMP | C6: 04 | D6: "SALE" => "04", if there is employee discount i.e., When PVCode is EMP | E6: EMPLOYEE SALES
A7: 11 | B7: "RETURN" => "02", | C7: 11 | D7: If Customer ID doesnot exists and if SLFTTP is 01 / Sale | E7: REGULAR RETURN
A8: 11 | B8: "RETURN" => "02", | C8: 12 | D8: If Customer ID exists and if SLFTTP is 01 / Sale | E8: TRADE RETURN
A9: 11 | B9: "RETURN" => "02", | C9: 45 | D9: If Tenders.Method = "GIFTCARD" | E9: RETURN IN GIFT CARD
A10: 87 | C10: 87 | E10: CURRENT TRANSACTION VOID
A11: 88 | C11: 01 | E11: POST VOID TRANSACTION
A13: TAX
A14: SLFTTP | C14: SLFLNT
A15: 01/02 11/12 | C15: XR | E15: BC PST
C16: XG | E16: GOODS AND SERVICES TAX
C17: XN | E17: HST NEW BRUNSWICK
C18: XF | E18: HST NEWFOUNDLAND
C19: XV | E19: HST NOVA SCOTIA
C20: XH | E20: HST ONTARIO
C21: XI | E21: HST PARTIAL ONTARIO
C22: XP | E22: HST PRINCE EDWARD ISLAND
C23: XM | E23: MANITOBA PST
C24: XQ | E24: QUEBEC Prov Tax
C25: XS | E25: SASK PST
A31: Price Vehicle Code | B31: Price Vehicle Reference
A32: EMP | B32: E99 where 99 is the discount % | C32: employee price
A33: FLR | B33: 6-digits flyer event # | C33: flyer price
A34: MAN | B34: D99 where 99 is the discount % | C34: manual discount
A35: OVD | B35: OVR | C35: override price
A36: PBK | B36: XXX | C36: price book price
A37: REG | B37: ORG | C37: regular retail price
A38: VOL | B38: VOL | C38: volume price
A39: CLR | B39: 6-digits clearance event #

Sheet J26_0539-S
A1: Field | B1: Description | C1: length | D1: SKU2 | F1: SKU line Orea Mapping | G1: SKU Line TTRee Output Logic | K1: Tax Line Orea Mapping | L1: Tax line TTRee logic
A2: SLFTTP | B2: Trans Type | C2: 2 | D2: =_xlfn.XLOOKUP($A2,Sheet3!$P:$P,Sheet3!$Q:$Q) -> 01 | E2: =_xlfn.XLOOKUP($A2,Sheet3!$D:$D,Sheet3!$E:$E) -> 01 | F2: Transaction.transactiontype | G2: Transaction.transactiontype Combined with Mapping Table | I2: =_xlfn.XLOOKUP($A2,Sheet3!$J:$J,Sheet3!$K:$K) -> 01 | K2: Same as SKU | L2: Same as SKU
A3: SLFLNT | B3: Line Type | C3: 2 | D3: =_xlfn.XLOOKUP($A3,Sheet3!$P:$P,Sheet3!$Q:$Q) -> 01 | E3: =_xlfn.XLOOKUP($A3,Sheet3!$D:$D,Sheet3!$E:$E) -> 01 | F3: Transaction.transactiontype | G3: Transaction.transactiontype Combined with Mapping Table | I3: =_xlfn.XLOOKUP($A3,Sheet3!$J:$J,Sheet3!$K:$K) -> XH | K3: N/A | L3: Calculculated based on Requirement mapping table (Tax Authority Sheet) Combination of column D & E = SLFLNT
A4: SLFTDT | B4: Trans Date | C4: 6 | D4: =_xlfn.XLOOKUP($A4,Sheet3!$P:$P,Sheet3!$Q:$Q) -> 260128 | E4: =_xlfn.XLOOKUP($A4,Sheet3!$D:$D,Sheet3!$E:$E) -> 260128 | F4: occurredAt (Provide a list of stores and MMS regions) | G4: Calculated Field based MMS Region occurredAt": "2026-01-13T17:00:53Z", YYMMDD "West - 8 Rest (ON&QC) -5" | I4: =_xlfn.XLOOKUP($A4,Sheet3!$J:$J,Sheet3!$K:$K) -> 260128 | K4: Same as SKU | L4: Same as SKU
A5: SLFTTM | B5: Trans Time | C5: 6 | D5: =_xlfn.XLOOKUP($A5,Sheet3!$P:$P,Sheet3!$Q:$Q) -> 144416 | E5: =_xlfn.XLOOKUP($A5,Sheet3!$D:$D,Sheet3!$E:$E) -> 144416 | F5: occurredAt (Provide a list of stores and MMS regions) | G5: Calculated Field based MMS Region occurredAt": "2026-01-13T17:00:53Z", "West - 8 Rest (ON&QC) -5" | I5: =_xlfn.XLOOKUP($A5,Sheet3!$J:$J,Sheet3!$K:$K) -> 144416 | K5: Same as SKU | L5: Same as SKU
A6: SLFCLK | B6: Store Clerk | C6: 5 | D6: =_xlfn.XLOOKUP($A6,Sheet3!$P:$P,Sheet3!$Q:$Q) -> 00085 | E6: =_xlfn.XLOOKUP($A6,Sheet3!$D:$D,Sheet3!$E:$E) -> 00085 | F6: workstation.registerId | G6: 5-digits number with Preceding zeros eg Register ID = 10 then send "00010" | I6: =_xlfn.XLOOKUP($A6,Sheet3!$J:$J,Sheet3!$K:$K) -> 00085 | K6: Same as SKU | L6: Same as SKU
A7: SLFREG | B7: Register ID | C7: 3 | D7: =_xlfn.XLOOKUP($A7,Sheet3!$P:$P,Sheet3!$Q:$Q) -> 085 | E7: =_xlfn.XLOOKUP($A7,Sheet3!$D:$D,Sheet3!$E:$E) -> 085 | F7: workstation.registerId | G7: 3-digits number with Preceding zeros eg Register ID = 10 then send "010" | I7: =_xlfn.XLOOKUP($A7,Sheet3!$J:$J,Sheet3!$K:$K) -> 085 | K7: Same as SKU | L7: Same as SKU
A8: SLFTTX | B8: Trans Number | C8: 5 | D8: =_xlfn.XLOOKUP($A8,Sheet3!$P:$P,Sheet3!$Q:$Q) -> 00604 | E8: =_xlfn.XLOOKUP($A8,Sheet3!$D:$D,Sheet3!$E:$E) -> 00604 | F8: Logic implemented on Tactill Mapped to: sequenceNumber | G8: Mapping | I8: =_xlfn.XLOOKUP($A8,Sheet3!$J:$J,Sheet3!$K:$K) -> 00604 | K8: Same as SKU | L8: Same as SKU
A9: SLFTSQ | B9: Trans Seq | C9: 5 | D9: =_xlfn.XLOOKUP($A9,Sheet3!$P:$P,Sheet3!$Q:$Q) -> 00002 | E9: =_xlfn.XLOOKUP($A9,Sheet3!$D:$D,Sheet3!$E:$E) -> 00001 | F9: N/A | G9: Implemented in TTRee to represent the line items being sent | I9: =_xlfn.XLOOKUP($A9,Sheet3!$J:$J,Sheet3!$K:$K) -> 00003 | K9: Same as SKU | L9: Same as SKU
A10: SLFSKU | B10: SKU Number | C10: 9 | D10: =_xlfn.XLOOKUP($A10,Sheet3!$P:$P,Sheet3!$Q:$Q) -> 000125728 | E10: =_xlfn.XLOOKUP($A10,Sheet3!$D:$D,Sheet3!$E:$E) -> 000272093 | F10: Item.sku | G10: Mapping | I10: =_xlfn.XLOOKUP($A10,Sheet3!$J:$J,Sheet3!$K:$K) -> 000000000 | K10: N/A | L10: Always 9 Zeros
A11: SLFQTY | B11: Quantity | C11: 9 | D11: =_xlfn.XLOOKUP($A11,Sheet3!$P:$P,Sheet3!$Q:$Q) -> 000000100 | E11: =_xlfn.XLOOKUP($A11,Sheet3!$D:$D,Sheet3!$E:$E) -> 000001200 | F11: Item.Quantity.value | G11: "Total quantity sold per SKU or Total quantity retrun per SKU Mapping it from quantity.value 9 digits with preceding zeros and multiplied by 100 | I11: =_xlfn.XLOOKUP($A11,Sheet3!$J:$J,Sheet3!$K:$K) -> 000000100 | K11: N/A | L11: Always '000000100'
A12: SLFQTN | B12: Negative Sign | C12: 1 | D12: =_xlfn.XLOOKUP($A12,Sheet3!$P:$P,Sheet3!$Q:$Q) | E12: =_xlfn.XLOOKUP($A12,Sheet3!$D:$D,Sheet3!$E:$E) | F12: N/A | G12: Calculated field For Sale always blank Return "-" | I12: =_xlfn.XLOOKUP($A12,Sheet3!$J:$J,Sheet3!$K:$K) | L12: Always Blank
A13: SLFORG | B13: Original Price | C13: 9 | D13: =_xlfn.XLOOKUP($A13,Sheet3!$P:$P,Sheet3!$Q:$Q) -> 000013900 | F13: Item.Pricing.OriginalUnitPrice | G13: 9-digits number with preceding 0s without decimal point Item.Pricing.OriginalUnitPrice | I13: =_xlfn.XLOOKUP($A13,Sheet3!$J:$J,Sheet3!$K:$K) -> 000000000 | L13: Always "000000000"
A14: SLFORN | B14: Negative Sign | C14: 1 | D14: =_xlfn.XLOOKUP($A14,Sheet3!$P:$P,Sheet3!$Q:$Q) | E14: =_xlfn.XLOOKUP($A14,Sheet3!$D:$D,Sheet3!$E:$E) | F14: N/A | G14: always blank | I14: =_xlfn.XLOOKUP($A14,Sheet3!$J:$J,Sheet3!$K:$K) | L14: Same as SKU
A15: SLFADC | B15: Ad Code | C15: 4 | D15: =_xlfn.XLOOKUP($A15,Sheet3!$P:$P,Sheet3!$Q:$Q) -> 0000 | E15: =_xlfn.XLOOKUP($A15,Sheet3!$D:$D,Sheet3!$E:$E) -> 0000 | F15: N/A | G15: #### when the POS price not = regular retail otherwise set to '0000' Calculated field i.e, When Orae PVCode = Reg then 4 Zeros if not send 4 #'s | I15: =_xlfn.XLOOKUP($A15,Sheet3!$J:$J,Sheet3!$K:$K) -> 0000 | L15: Always "0000"
A16: SLFADP | B16: Ad Price | C16: 9 | D16: =_xlfn.XLOOKUP($A16,Sheet3!$P:$P,Sheet3!$Q:$Q) -> 000000000 | E16: =_xlfn.XLOOKUP($A16,Sheet3!$D:$D,Sheet3!$E:$E) -> 000000000 | F16: Item.Pricing.UnitPrice | G16: Calculated Field When PVCode is REG Or MAN then send 9 Zeros If not 9-digits number without decimal point Mapping with Preceding Zeros | I16: =_xlfn.XLOOKUP($A16,Sheet3!$J:$J,Sheet3!$K:$K) -> 000000000 | L16: Always "00000000"
A17: SLFADN | B17: Negative Sign | C17: 1 | D17: =_xlfn.XLOOKUP($A17,Sheet3!$P:$P,Sheet3!$Q:$Q) | E17: =_xlfn.XLOOKUP($A17,Sheet3!$D:$D,Sheet3!$E:$E) | F17: always blank | G17: always blank | I17: =_xlfn.XLOOKUP($A17,Sheet3!$J:$J,Sheet3!$K:$K) | K17: Same as SKU | L17: Same as SKU
A18: SLFOVR | B18: Override Price | C18: 9 | D18: =_xlfn.XLOOKUP($A18,Sheet3!$P:$P,Sheet3!$Q:$Q) -> 000000000 | E18: =_xlfn.XLOOKUP($A18,Sheet3!$D:$D,Sheet3!$E:$E) -> 000000000 | F18: Item.Pricing.priceoverride | G18: Calculated If the override price exists then use Orae Mapping if not send 9 Zeros | I18: =_xlfn.XLOOKUP($A18,Sheet3!$J:$J,Sheet3!$K:$K) -> 000000000 | L18: Always "00000000"
A19: SLFOVN | B19: Negative Sign | C19: 1 | D19: =_xlfn.XLOOKUP($A19,Sheet3!$P:$P,Sheet3!$Q:$Q) | E19: =_xlfn.XLOOKUP($A19,Sheet3!$D:$D,Sheet3!$E:$E) | F19: N/A | G19: always blank | I19: =_xlfn.XLOOKUP($A19,Sheet3!$J:$J,Sheet3!$K:$K) | K19: Same as SKU | L19: Same as SKU
A20: SLFDST | B20: Discount Type | C20: 2 | D20: =_xlfn.XLOOKUP($A20,Sheet3!$P:$P,Sheet3!$Q:$Q) | E20: =_xlfn.XLOOKUP($A20,Sheet3!$D:$D,Sheet3!$E:$E) | F20: N/A | G20: always blank | I20: =_xlfn.XLOOKUP($A20,Sheet3!$J:$J,Sheet3!$K:$K) | L20: Always Blank
A21: SLFDSA | B21: Discount Amount | C21: 9 | D21: =_xlfn.XLOOKUP($A21,Sheet3!$P:$P,Sheet3!$Q:$Q) -> 000000000 | E21: =_xlfn.XLOOKUP($A21,Sheet3!$D:$D,Sheet3!$E:$E) -> 000000000 | F21: N/A | G21: always set to 9 Zeros | I21: =_xlfn.XLOOKUP($A21,Sheet3!$J:$J,Sheet3!$K:$K) -> 000000000 | L21: Always "00000000"
A22: SLFDSN | B22: Negative Sign | C22: 1 | D22: =_xlfn.XLOOKUP($A22,Sheet3!$P:$P,Sheet3!$Q:$Q) | E22: =_xlfn.XLOOKUP($A22,Sheet3!$D:$D,Sheet3!$E:$E) | F22: N/A | G22: always blank | I22: =_xlfn.XLOOKUP($A22,Sheet3!$J:$J,Sheet3!$K:$K) | L22: Same as SKU
A23: SLFSEL | B23: Item Sell Price | C23: 9 | D23: =_xlfn.XLOOKUP($A23,Sheet3!$P:$P,Sheet3!$Q:$Q) -> 000013900 | E23: =_xlfn.XLOOKUP($A23,Sheet3!$D:$D,Sheet3!$E:$E) -> 000000083 | F23: Item.Pricing.Unitprice | G23: Calculated field (Provide Logic) Take the mapping price if override price = zero; otherwise use override price | I23: =_xlfn.XLOOKUP($A23,Sheet3!$J:$J,Sheet3!$K:$K) -> 000001936 | K23: Tax.amount.value | L23: Calculated Total Tax Amount
A24: SLFSLN | B24: Negative Sign | C24: 1 | D24: =_xlfn.XLOOKUP($A24,Sheet3!$P:$P,Sheet3!$Q:$Q) | E24: =_xlfn.XLOOKUP($A24,Sheet3!$D:$D,Sheet3!$E:$E) | F24: N/A | G24: always blank | I24: =_xlfn.XLOOKUP($A24,Sheet3!$J:$J,Sheet3!$K:$K) | K24: Always Blank | L24: Same as SKU
A25: SLFEXT | B25: Extended Value | C25: 11 | D25: =_xlfn.XLOOKUP($A25,Sheet3!$P:$P,Sheet3!$Q:$Q) -> 00000013900 | E25: =_xlfn.XLOOKUP($A25,Sheet3!$D:$D,Sheet3!$E:$E) -> 00000000996 | F25: N/A | G25: Calculated Field Item.quanitity.value * Item.Pricing.UnitPrice If ovreride exists then "Calculated Field Item.quanitity.value * Item.Pricing.PriceOverride | I25: =_xlfn.XLOOKUP($A25,Sheet3!$J:$J,Sheet3!$K:$K) -> 00000001936 | K25: Tax.amount.value | L25: Calculated Total Tax Amount
A26: SLFEXN | B26: Negative Sign | C26: 1 | D26: =_xlfn.XLOOKUP($A26,Sheet3!$P:$P,Sheet3!$Q:$Q) | E26: =_xlfn.XLOOKUP($A26,Sheet3!$D:$D,Sheet3!$E:$E) | F26: N/A | G26: Calculated field "blank means positive set to - for return" | I26: =_xlfn.XLOOKUP($A26,Sheet3!$J:$J,Sheet3!$K:$K) | K26: Calculated field | L26: Same as SKU
A27: SLFTX1 | B27: Charged TAX1 Y/N | C27: 1 | D27: =_xlfn.XLOOKUP($A27,Sheet3!$P:$P,Sheet3!$Q:$Q) -> N | E27: =_xlfn.XLOOKUP($A27,Sheet3!$D:$D,Sheet3!$E:$E) -> N | F27: N/A | G27: Calculated field Default to N Y for SKY with PST charged | I27: =_xlfn.XLOOKUP($A27,Sheet3!$J:$J,Sheet3!$K:$K) -> N | K27: N/A | L27: Always "N"
A28: SLFTX2 | B28: Charged TAX2 Y/N | C28: 1 | D28: =_xlfn.XLOOKUP($A28,Sheet3!$P:$P,Sheet3!$Q:$Q) -> N | E28: =_xlfn.XLOOKUP($A28,Sheet3!$D:$D,Sheet3!$E:$E) -> N | F28: N/A | G28: Calculated field Default to N Y for SKU with GST | I28: =_xlfn.XLOOKUP($A28,Sheet3!$J:$J,Sheet3!$K:$K) -> N | K28: N/A | L28: Always "N"
A29: SLFTX3 | B29: Charged TAX3 Y/N | C29: 1 | D29: =_xlfn.XLOOKUP($A29,Sheet3!$P:$P,Sheet3!$Q:$Q) -> Y | E29: =_xlfn.XLOOKUP($A29,Sheet3!$D:$D,Sheet3!$E:$E) -> Y | F29: N/A | G29: Calculated field Default to N Y for SKU with HST | I29: =_xlfn.XLOOKUP($A29,Sheet3!$J:$J,Sheet3!$K:$K) -> N | K29: N/A | L29: Always "N"
A30: SLFTX4 | B30: Charged TAX4 Y/N | C30: 1 | D30: =_xlfn.XLOOKUP($A30,Sheet3!$P:$P,Sheet3!$Q:$Q) -> N | E30: =_xlfn.XLOOKUP($A30,Sheet3!$D:$D,Sheet3!$E:$E) -> N | F30: N/A | G30: Calculated field Default to N Y for SKU with Partial HST | I30: =_xlfn.XLOOKUP($A30,Sheet3!$J:$J,Sheet3!$K:$K) -> N | K30: N/A | L30: Always "N"
A31: SLFRFC | B31: Reference Code | C31: 1 | D31: =_xlfn.XLOOKUP($A31,Sheet3!$P:$P,Sheet3!$Q:$Q) | E31: =_xlfn.XLOOKUP($A31,Sheet3!$D:$D,Sheet3!$E:$E) | F31: N/A | G31: always blank | I31: =_xlfn.XLOOKUP($A31,Sheet3!$J:$J,Sheet3!$K:$K) | K31: N/A | L31: Same as SKU
A32: SLFRFD | B32: Reference Desc | C32: 16 | D32: =_xlfn.XLOOKUP($A32,Sheet3!$P:$P,Sheet3!$Q:$Q) | E32: =_xlfn.XLOOKUP($A32,Sheet3!$D:$D,Sheet3!$E:$E) | F32: N/A | G32: always blank | I32: =_xlfn.XLOOKUP($A32,Sheet3!$J:$J,Sheet3!$K:$K) | K32: N/A | L32: Same as SKU
A33: SLFUPC | B33: UPC Code | C33: 13 | D33: =_xlfn.XLOOKUP($A33,Sheet3!$P:$P,Sheet3!$Q:$Q) -> 0000000000000 | E33: =_xlfn.XLOOKUP($A33,Sheet3!$D:$D,Sheet3!$E:$E) -> 0000000000000 | F33: item.gtin | G33: item.gtin If no value, set it to 13 Zeros | I33: =_xlfn.XLOOKUP($A33,Sheet3!$J:$J,Sheet3!$K:$K) -> 0000000000000 | K33: N/A | L33: Always 13 Zeros
A34: SLFSPS | B34: Sales Person | C34: 5 | D34: =_xlfn.XLOOKUP($A34,Sheet3!$P:$P,Sheet3!$Q:$Q) -> 00085 | E34: =_xlfn.XLOOKUP($A34,Sheet3!$D:$D,Sheet3!$E:$E) -> 00085 | F34: SCO - Workstation.RegisterID ACO- actor.cashier.loginid | G34: Calculated If register Starts with 8 then SCO if not its ACO SCO = use register ID ampping - prefix Zeros upto 5 digits ACO = Mapping default 5 0s | I34: =_xlfn.XLOOKUP($A34,Sheet3!$J:$J,Sheet3!$K:$K) -> 00085 | K34: Same as SKU | L34: Same as SKU
A35: SLFSTS | B35: Status | C35: 1 | D35: =_xlfn.XLOOKUP($A35,Sheet3!$P:$P,Sheet3!$Q:$Q) | E35: =_xlfn.XLOOKUP($A35,Sheet3!$D:$D,Sheet3!$E:$E) | F35: N/A | G35: always blank | I35: =_xlfn.XLOOKUP($A35,Sheet3!$J:$J,Sheet3!$K:$K) | K35: N/A | L35: Same as SKU
A36: 2 | B36: Zip Code | C36: 10 | D36: =_xlfn.XLOOKUP($A36,Sheet3!$P:$P,Sheet3!$Q:$Q) -> #N/A | E36: =_xlfn.XLOOKUP($A36,Sheet3!$D:$D,Sheet3!$E:$E) -> #N/A | F36: transaction.items[i].attributes["x-epp-coverage-identifier"] | G36: Mappiing | H36: High | I36: =_xlfn.XLOOKUP($A36,Sheet3!$J:$J,Sheet3!$K:$K) -> #N/A | K36: N/A | L36: Always 10 Zeros 9 spaced + 0 i.e, " 0"
A37: SLFCNM | B37: Customer Name | C37: 35 | D37: =_xlfn.XLOOKUP($A37,Sheet3!$P:$P,Sheet3!$Q:$Q) | E37: =_xlfn.XLOOKUP($A37,Sheet3!$D:$D,Sheet3!$E:$E) | F37: N/A | G37: always blank | I37: =_xlfn.XLOOKUP($A37,Sheet3!$J:$J,Sheet3!$K:$K) | K37: N/A | L37: Always Blank
A38: SLFNUM | B38: Customer Number | C38: 10 | D38: =_xlfn.XLOOKUP($A38,Sheet3!$P:$P,Sheet3!$Q:$Q) | E38: =_xlfn.XLOOKUP($A38,Sheet3!$D:$D,Sheet3!$E:$E) | F38: Customer.customerIdToken | G38: Mapping default to blank | I38: =_xlfn.XLOOKUP($A38,Sheet3!$J:$J,Sheet3!$K:$K) | K38: Same as SKU | L38: Same as SKU
A39: SLFRSN | B39: Reason Code | C39: 16 | D39: =_xlfn.XLOOKUP($A39,Sheet3!$P:$P,Sheet3!$Q:$Q) | E39: =_xlfn.XLOOKUP($A39,Sheet3!$D:$D,Sheet3!$E:$E) | F39: ??? | G39: return reason code (RRT0) + Mapping price override reason code (POV0) + Mapping post voided reason code (VOD0) left justified" Default to Blank | I39: =_xlfn.XLOOKUP($A39,Sheet3!$J:$J,Sheet3!$K:$K) | K39: N/A | L39: Always Blank
A40: SLFOSP | B40: Original Salesperson | C40: 5 | D40: =_xlfn.XLOOKUP($A40,Sheet3!$P:$P,Sheet3!$Q:$Q) -> 00000 | E40: =_xlfn.XLOOKUP($A40,Sheet3!$D:$D,Sheet3!$E:$E) -> 00000 | F40: N/A | G40: always 5 zeros | I40: =_xlfn.XLOOKUP($A40,Sheet3!$J:$J,Sheet3!$K:$K) -> 00000 | K40: N/A | L40: Same as SKU
A41: SLFOST | B41: Original Store | C41: 5 | D41: =_xlfn.XLOOKUP($A41,Sheet3!$P:$P,Sheet3!$Q:$Q) -> 00000 | E41: =_xlfn.XLOOKUP($A41,Sheet3!$D:$D,Sheet3!$E:$E) -> 00000 | F41: N/A | G41: always '5 Zeros | I41: =_xlfn.XLOOKUP($A41,Sheet3!$J:$J,Sheet3!$K:$K) -> 00000 | K41: N/A | L41: Same as SKU
A42: SLFGDA | B42: Grp Disc Amount | C42: 9 | D42: =_xlfn.XLOOKUP($A42,Sheet3!$P:$P,Sheet3!$Q:$Q) -> 000000000 | E42: =_xlfn.XLOOKUP($A42,Sheet3!$D:$D,Sheet3!$E:$E) -> 000000000 | F42: N/A | G42: always 9 Zeros | I42: =_xlfn.XLOOKUP($A42,Sheet3!$J:$J,Sheet3!$K:$K) -> 000000000 | K42: N/A | L42: Same as SKU
A43: SLFGDS | B43: Grp Disc Sign | C43: 1 | D43: =_xlfn.XLOOKUP($A43,Sheet3!$P:$P,Sheet3!$Q:$Q) | E43: =_xlfn.XLOOKUP($A43,Sheet3!$D:$D,Sheet3!$E:$E) | F43: N/A | G43: always blanks | I43: =_xlfn.XLOOKUP($A43,Sheet3!$J:$J,Sheet3!$K:$K) | K43: N/A | L43: Same as SKU
A44: SLFGDR | B44: Grp Disc Reason | C44: 2 | D44: =_xlfn.XLOOKUP($A44,Sheet3!$P:$P,Sheet3!$Q:$Q) -> 00 | E44: =_xlfn.XLOOKUP($A44,Sheet3!$D:$D,Sheet3!$E:$E) -> 00 | F44: N/A | G44: always 2 Zeros | I44: =_xlfn.XLOOKUP($A44,Sheet3!$J:$J,Sheet3!$K:$K) -> 00 | K44: N/A | L44: Same as SKU
A45: SLFRDR | B45: Reg Disc Reason | C45: 2 | D45: =_xlfn.XLOOKUP($A45,Sheet3!$P:$P,Sheet3!$Q:$Q) -> 00 | E45: =_xlfn.XLOOKUP($A45,Sheet3!$D:$D,Sheet3!$E:$E) -> 00 | F45: N/A | G45: Calculated field set to 'I2' when PVC = 'MAN'; else set to '00' | I45: =_xlfn.XLOOKUP($A45,Sheet3!$J:$J,Sheet3!$K:$K) -> 00 | K45: N/A | L45: Always 2 Zeros
A46: SLFSCN | B46: Item Scanned Y/N | C46: 1 | D46: =_xlfn.XLOOKUP($A46,Sheet3!$P:$P,Sheet3!$Q:$Q) -> N | E46: =_xlfn.XLOOKUP($A46,Sheet3!$D:$D,Sheet3!$E:$E) -> N | F46: N/A | G46: Calculated field If item.gitin value is greater than 0 then Y if not N | H46: Med | I46: =_xlfn.XLOOKUP($A46,Sheet3!$J:$J,Sheet3!$K:$K) -> N | K46: N/A | L46: Always Blank
A47: SLFACD | B47: Tax Auth Code | C47: 6 | D47: =_xlfn.XLOOKUP($A47,Sheet3!$P:$P,Sheet3!$Q:$Q) -> ON | E47: =_xlfn.XLOOKUP($A47,Sheet3!$D:$D,Sheet3!$E:$E) -> ON | F47: N/A | G47: always blanks | I47: =_xlfn.XLOOKUP($A47,Sheet3!$J:$J,Sheet3!$K:$K) -> HON | K47: Taxes.Jurisdiction.region | L47: Find mapping in Tax Authority Sheet If tax line type = column C then send associated column b Mapping
A48: SLFTCD | B48: Tax Rate Code | C48: 6 | D48: =_xlfn.XLOOKUP($A48,Sheet3!$P:$P,Sheet3!$Q:$Q) | E48: =_xlfn.XLOOKUP($A48,Sheet3!$D:$D,Sheet3!$E:$E) | F48: N/A | G48: always blanks | H48: Critical | I48: =_xlfn.XLOOKUP($A48,Sheet3!$J:$J,Sheet3!$K:$K) -> HST | K48: Taxes.taxcode | L48: "Find mapping in Tax Authority Sheet If tax line type = column C then send associated column d" Mapping
A49: SLFTE1 | B49: Tax Exempt ID 1 | C49: 20 | D49: =_xlfn.XLOOKUP($A49,Sheet3!$P:$P,Sheet3!$Q:$Q) | E49: =_xlfn.XLOOKUP($A49,Sheet3!$D:$D,Sheet3!$E:$E) | F49: N/A | G49: always blanks | I49: =_xlfn.XLOOKUP($A49,Sheet3!$J:$J,Sheet3!$K:$K) | K49: always blanks | L49: always blanks
A50: SLFTE2 | B50: Tax Exempt ID 2 | C50: 20 | D50: =_xlfn.XLOOKUP($A50,Sheet3!$P:$P,Sheet3!$Q:$Q) | E50: =_xlfn.XLOOKUP($A50,Sheet3!$D:$D,Sheet3!$E:$E) | F50: N/A | G50: always blanks | I50: =_xlfn.XLOOKUP($A50,Sheet3!$J:$J,Sheet3!$K:$K) | K50: always blanks | L50: always blanks
A51: SLFTEN | B51: Tax Exemption Name | C51: 35 | D51: =_xlfn.XLOOKUP($A51,Sheet3!$P:$P,Sheet3!$Q:$Q) | E51: =_xlfn.XLOOKUP($A51,Sheet3!$D:$D,Sheet3!$E:$E) | F51: N/A | G51: always blanks | I51: =_xlfn.XLOOKUP($A51,Sheet3!$J:$J,Sheet3!$K:$K) | K51: always blanks | L51: always blanks
A52: SLFPVC | B52: Price Vehicle Code | C52: 4 | D52: =_xlfn.XLOOKUP($A52,Sheet3!$P:$P,Sheet3!$Q:$Q) -> REG | E52: =_xlfn.XLOOKUP($A52,Sheet3!$D:$D,Sheet3!$E:$E) -> REG | F52: LineItem.pricing.priceVehicle | G52: Calculated field " The value for this field will be a combination of 2 values separated with :. Ex: ""VOL:VOL"" ""REG:ORG"" ""OVD:OVR"" And left hand side will go into - SLFPVC" | I52: =_xlfn.XLOOKUP($A52,Sheet3!$J:$J,Sheet3!$K:$K) | K52: always blanks | L52: always blanks
A53: SLFREF | B53: Price Vehicle Reference | C53: 12 | D53: =_xlfn.XLOOKUP($A53,Sheet3!$P:$P,Sheet3!$Q:$Q) -> ORG | E53: =_xlfn.XLOOKUP($A53,Sheet3!$D:$D,Sheet3!$E:$E) -> ORG | F53: N/A | G53: Calculated field "LineItem.pricing.priceVehicle The value for this field will be a combination of 2 values separated with :. Ex: ""VOL:VOL"" ""REG:ORG"" ""OVD:OVR"" right hand side will go into - SLFREF" | I53: =_xlfn.XLOOKUP($A53,Sheet3!$J:$J,Sheet3!$K:$K) | L53: always blanks
A54: SLFORT | B54: Original Retail | C54: 9 | D54: =_xlfn.XLOOKUP($A54,Sheet3!$P:$P,Sheet3!$Q:$Q) -> 000013900 | E54: =_xlfn.XLOOKUP($A54,Sheet3!$D:$D,Sheet3!$E:$E) -> 000000083 | F54: Item.Pricing.OriginalUnitPrice | G54: Mapping | I54: =_xlfn.XLOOKUP($A54,Sheet3!$J:$J,Sheet3!$K:$K) -> 000000000 | L54: Alwyays 9 0s
A55: SLFOPN | B55: Negative Sign | C55: 1 | D55: =_xlfn.XLOOKUP($A55,Sheet3!$P:$P,Sheet3!$Q:$Q) | E55: =_xlfn.XLOOKUP($A55,Sheet3!$D:$D,Sheet3!$E:$E) | F55: N/A | G55: always blank | I55: =_xlfn.XLOOKUP($A55,Sheet3!$J:$J,Sheet3!$K:$K) | L55: always blanks
A56: SLFOTS | B56: Original TX Store | C56: 5 | D56: =_xlfn.XLOOKUP($A56,Sheet3!$P:$P,Sheet3!$Q:$Q) -> 00000 | E56: =_xlfn.XLOOKUP($A56,Sheet3!$D:$D,Sheet3!$E:$E) -> 00000 | F56: Store.StoreID | G56: Calculated field If SLFTTP = 01 then set to 5 Zeros If SLFTTP = 11 then mapping | I56: =_xlfn.XLOOKUP($A56,Sheet3!$J:$J,Sheet3!$K:$K) -> 00000 | L56: Always 5 zeros
A57: SLFOTD | B57: Original TX Date | C57: 6 | D57: =_xlfn.XLOOKUP($A57,Sheet3!$P:$P,Sheet3!$Q:$Q) -> 000000 | E57: =_xlfn.XLOOKUP($A57,Sheet3!$D:$D,Sheet3!$E:$E) -> 000000 | F57: OccuredAt | G57: Calculated field If SLFTTP = 01 then set to 6 Zeros If SLFTTP = 11 then mapping | I57: =_xlfn.XLOOKUP($A57,Sheet3!$J:$J,Sheet3!$K:$K) -> 000000 | L57: Always 6 zeros
A58: SLFOTR | B58: Original TX Register | C58: 3 | D58: =_xlfn.XLOOKUP($A58,Sheet3!$P:$P,Sheet3!$Q:$Q) -> 000 | E58: =_xlfn.XLOOKUP($A58,Sheet3!$D:$D,Sheet3!$E:$E) -> 000 | F58: workstation.registerId | G58: Calculated field If SLFTTP = 01 then set to 3 Zeros If SLFTTP = 11 then mapping | I58: =_xlfn.XLOOKUP($A58,Sheet3!$J:$J,Sheet3!$K:$K) -> 000 | L58: Always 3 zeros
A59: SLFOTT | B59: Original TX TTX# | C59: 5 | D59: =_xlfn.XLOOKUP($A59,Sheet3!$P:$P,Sheet3!$Q:$Q) -> 00000 | E59: =_xlfn.XLOOKUP($A59,Sheet3!$D:$D,Sheet3!$E:$E) -> 00000 | F59: SourceTransactionID | G59: Calculated field If SLFTTP = 01 then set to 5 Zeros If SLFTTP = 11 then mapping | I59: =_xlfn.XLOOKUP($A59,Sheet3!$J:$J,Sheet3!$K:$K) -> 00000 | L59: Always 5 zeros
A60: SLFPLC | B60: Polled Store | C60: 5 | D60: =_xlfn.XLOOKUP($A60,Sheet3!$P:$P,Sheet3!$Q:$Q) -> 55010 | E60: =_xlfn.XLOOKUP($A60,Sheet3!$D:$D,Sheet3!$E:$E) -> 55010 | F60: BusinessContext.Store.StoreID | G60: Mapping | I60: =_xlfn.XLOOKUP($A60,Sheet3!$J:$J,Sheet3!$K:$K) -> 55010 | L60: Same as SKU
A61: SLFPCN | B61: Poll Cen | C61: 1 | D61: =_xlfn.XLOOKUP($A61,Sheet3!$P:$P,Sheet3!$Q:$Q) -> 1 | E61: =_xlfn.XLOOKUP($A61,Sheet3!$D:$D,Sheet3!$E:$E) -> 1 | F61: N/A | G61: Always 1 | I61: =_xlfn.XLOOKUP($A61,Sheet3!$J:$J,Sheet3!$K:$K) -> 1 | L61: Same as SKU
A62: SLFPDT | B62: Poll Date | C62: 6 | D62: =_xlfn.XLOOKUP($A62,Sheet3!$P:$P,Sheet3!$Q:$Q) -> 260128 | E62: =_xlfn.XLOOKUP($A62,Sheet3!$D:$D,Sheet3!$E:$E) -> 260128 | F62: businessDay | G62: Mapping (YYMMDD) | I62: =_xlfn.XLOOKUP($A62,Sheet3!$J:$J,Sheet3!$K:$K) -> 260128 | L62: Same as SKU
A63: SLFCCN | B63: Create Cen | C63: 1 | D63: =_xlfn.XLOOKUP($A63,Sheet3!$P:$P,Sheet3!$Q:$Q) -> 1 | E63: =_xlfn.XLOOKUP($A63,Sheet3!$D:$D,Sheet3!$E:$E) -> 1 | F63: N/A | G63: Always 1 | I63: =_xlfn.XLOOKUP($A63,Sheet3!$J:$J,Sheet3!$K:$K) -> 1 | L63: Same as SKU
A64: SLFCDT | B64: Create Date | C64: 6 | D64: =_xlfn.XLOOKUP($A64,Sheet3!$P:$P,Sheet3!$Q:$Q) -> 260128 | E64: =_xlfn.XLOOKUP($A64,Sheet3!$D:$D,Sheet3!$E:$E) -> 260128 | F64: occurredAt (Provide a list of stores and MMS regions) | G64: Calculated Field based MMS Region occurredAt": "2026-01-13T17:00:53Z", YYMMDD "West - 8 Rest (ON&QC) -5" | I64: =_xlfn.XLOOKUP($A64,Sheet3!$J:$J,Sheet3!$K:$K) -> 260128 | L64: Same as SKU
... A78: SLFECN | B78: Employee Card # | C78: 13 | D78: =_xlfn.XLOOKUP($A78,Sheet3!$P:$P,Sheet3!$Q:$Q) -> 0 | E78: =_xlfn.XLOOKUP($A78,Sheet3!$D:$D,Sheet3!$E:$E) -> 0 | F78: N/A | G78: always blank | I78: =_xlfn.XLOOKUP($A78,Sheet3!$J:$J,Sheet3!$K:$K) -> #N/A | L78: Same as SKU

Sheet J26_0539-T
F1: jan 22 | H1: PPR Jan 23 - Multi Products | J1: Jan 26 Multiple SKU
A2: Field | B2: Description | C2: length | D2: Priority | F2: TTress | G2: Fixes Needed | H2: TTress | I2: Fixes Needed | K2: Tender line Orea Mapping | L2: Tender Line TTRee Logic
A3: TNFTTP | B3: Transaction Type | C3: 2 | E3: =_xlfn.XLOOKUP($A3,Sheet3!$V:$V,Sheet3!$W:$W) -> 01 | F3: 01 | H3: =_xlfn.IFNA(_xlfn.XLOOKUP($A3,'T-00531'!$D:$D,'T-00531'!$E:$E),"Not in Sheet1") -> 01 | J3: =_xlfn.XLOOKUP($A2,Sheet3!$P:$P,Sheet3!$Q:$Q) -> #N/A | K3: Same as SLFTTP | L3: Same as SLFTTP
A4: TNFTDT | B4: Transaction Date | C4: 6 | E4: =_xlfn.XLOOKUP($A4,Sheet3!$V:$V,Sheet3!$W:$W) -> 260128 | F4: 260122 | H4: =_xlfn.IFNA(_xlfn.XLOOKUP($A4,'T-00531'!$D:$D,'T-00531'!$E:$E),"Not in Sheet1") -> 260123 | J4: =_xlfn.XLOOKUP($A4,Sheet3!$P:$P,Sheet3!$Q:$Q) -> #N/A | K4: occurredAt (Provide a list of stores and MMS regions) | L4: Calculated Field based MMS Region occurredAt": "2026-01-13T17:00:53Z", YYMMDD "West - 8 Rest (ON&QC) -5"
A5: TNFTTM | B5: Transaction Time | C5: 6 | D5: Critical | E5: =_xlfn.XLOOKUP($A5,Sheet3!$V:$V,Sheet3!$W:$W) -> 144416 | F5: 125002 | G5: 075002 | H5: =_xlfn.IFNA(_xlfn.XLOOKUP($A5,'T-00531'!$D:$D,'T-00531'!$E:$E),"Not in Sheet1") -> 154417 | J5: =_xlfn.XLOOKUP($A5,Sheet3!$P:$P,Sheet3!$Q:$Q) -> #N/A | K5: occurredAt (Provide a list of stores and MMS regions) | L5: Calculated Field based MMS Region occurredAt": "2026-01-13T17:00:53Z", HHMMSS "West - 8 Rest (ON&QC) -5"
A6: TNFCLK | B6: Clerk | C6: 5 | E6: =_xlfn.XLOOKUP($A6,Sheet3!$V:$V,Sheet3!$W:$W) -> 00085 | F6: 00081 | H6: =_xlfn.IFNA(_xlfn.XLOOKUP($A6,'T-00531'!$D:$D,'T-00531'!$E:$E),"Not in Sheet1") -> 00085 | J6: =_xlfn.XLOOKUP($A6,Sheet3!$P:$P,Sheet3!$Q:$Q) -> #N/A | K6: workstation.registerId | L6: 5-digits number with Preceding zeros eg Register ID = 10 then send "00010"
A7: TNFREG | B7: Register ID | C7: 3 | E7: =_xlfn.XLOOKUP($A7,Sheet3!$V:$V,Sheet3!$W:$W) -> 085 | F7: 081 | H7: =_xlfn.IFNA(_xlfn.XLOOKUP($A7,'T-00531'!$D:$D,'T-00531'!$E:$E),"Not in Sheet1") -> 085 | J7: =_xlfn.XLOOKUP($A7,Sheet3!$P:$P,Sheet3!$Q:$Q) -> #N/A | K7: workstation.registerId | L7: 3-digits number with Preceding zeros eg Register ID = 10 then send "010"
A8: TNFTTX | B8: Transaction Number | C8: 5 | E8: =_xlfn.XLOOKUP($A8,Sheet3!$V:$V,Sheet3!$W:$W) -> 00604 | F8: 00129 | H8: =_xlfn.IFNA(_xlfn.XLOOKUP($A8,'T-00531'!$D:$D,'T-00531'!$E:$E),"Not in Sheet1") -> 00531 | J8: =_xlfn.XLOOKUP($A8,Sheet3!$P:$P,Sheet3!$Q:$Q) -> #N/A | K8: Logic implemented on Tactill Mapped to: sequenceNumber | L8: Mapping
A9: TNFTSQ | B9: Transaction Seq | C9: 5 | E9: =_xlfn.XLOOKUP($A9,Sheet3!$V:$V,Sheet3!$W:$W) -> 00004 | F9: 00003 | H9: =_xlfn.IFNA(_xlfn.XLOOKUP($A9,'T-00531'!$D:$D,'T-00531'!$E:$E),"Not in Sheet1") -> 00005 | J9: =_xlfn.XLOOKUP($A9,Sheet3!$P:$P,Sheet3!$Q:$Q) -> #N/A | K9: N/A | L9: Implemented in TTRee to represent the line items being sent
A10: TNFFCD | B10: Fund Code | C10: 2 | E10: =_xlfn.XLOOKUP($A10,Sheet3!$V:$V,Sheet3!$W:$W) -> VI | F10: VI | H10: =_xlfn.IFNA(_xlfn.XLOOKUP($A10,'T-00531'!$D:$D,'T-00531'!$E:$E),"Not in Sheet1") -> VI | J10: =_xlfn.XLOOKUP($A10,Sheet3!$P:$P,Sheet3!$Q:$Q) -> #N/A | K10: tenders.card.scheme | L10: Mapping combined with fundcode table
A11: TNFAMT | B11: Amount | C11: 11 | E11: =_xlfn.XLOOKUP($A11,Sheet3!$V:$V,Sheet3!$W:$W) -> 00000016832 | F11: 00000000506 | H11: =_xlfn.IFNA(_xlfn.XLOOKUP($A11,'T-00531'!$D:$D,'T-00531'!$E:$E),"Not in Sheet1") -> 00000002586 | J11: =_xlfn.XLOOKUP($A11,Sheet3!$P:$P,Sheet3!$Q:$Q) -> #N/A | K11: tender.amount.value | L11: Mapping
A12: TNFAMN | B12: Negative Sign | C12: 1 | E12: =_xlfn.XLOOKUP($A12,Sheet3!$V:$V,Sheet3!$W:$W) | F12: Blank | H12: =_xlfn.IFNA(_xlfn.XLOOKUP($A12,'T-00531'!$D:$D,'T-00531'!$E:$E),"Not in Sheet1") | J12: =_xlfn.XLOOKUP($A12,Sheet3!$P:$P,Sheet3!$Q:$Q) -> #N/A | K12: N/A | L12: Calculated Sales = Always Blank Returns = "-"
A13: TNFCCD | B13: Credit Card | C13: 19 | D13: Critical | E13: =_xlfn.XLOOKUP($A13,Sheet3!$V:$V,Sheet3!$W:$W) -> ***************4902 | F13: VISA3332 | G13: ************3332 | H13: =_xlfn.IFNA(_xlfn.XLOOKUP($A13,'T-00531'!$D:$D,'T-00531'!$E:$E),"Not in Sheet1") -> ***************4903 | J13: =_xlfn.XLOOKUP($A13,Sheet3!$P:$P,Sheet3!$Q:$Q) -> #N/A | K13: tenders.card.last 4 | L13: Calculated need to apply prefix of 12 *s to Mapping
A14: TNFEXP | B14: Card Exp. Date | C14: 4 | E14: =_xlfn.XLOOKUP($A14,Sheet3!$V:$V,Sheet3!$W:$W) -> 0000 | F14: 0000 | H14: =_xlfn.IFNA(_xlfn.XLOOKUP($A14,'T-00531'!$D:$D,'T-00531'!$E:$E),"Not in Sheet1") -> 0000 | J14: =_xlfn.XLOOKUP($A14,Sheet3!$P:$P,Sheet3!$Q:$Q) -> #N/A | K14: N/A | L14: Always 4 Zeros
A15: TNFAUT | B15: Auth Number | C15: 6 | E15: =_xlfn.XLOOKUP($A15,Sheet3!$V:$V,Sheet3!$W:$W) -> 066851 | F15: 055794 | H15: =_xlfn.IFNA(_xlfn.XLOOKUP($A15,'T-00531'!$D:$D,'T-00531'!$E:$E),"Not in Sheet1") -> 066851 | J15: =_xlfn.XLOOKUP($A15,Sheet3!$P:$P,Sheet3!$Q:$Q) -> #N/A | K15: Tenders.Card.AuthCode | L15: Mapping For Flexity - Send only last 6 digits
A16: TNFRFC | B16: Reference Code | C16: 1 | D16: Critical | E16: =_xlfn.XLOOKUP($A16,Sheet3!$V:$V,Sheet3!$W:$W) | F16: T | G16: Blank | H16: =_xlfn.IFNA(_xlfn.XLOOKUP($A16,'T-00531'!$D:$D,'T-00531'!$E:$E),"Not in Sheet1") | J16: =_xlfn.XLOOKUP($A16,Sheet3!$P:$P,Sheet3!$Q:$Q) -> #N/A | K16: N/A | L16: Always blank
A17: TNFRDS | B17: Reference Desc | C17: 16 | D17: Critical | E17: =_xlfn.XLOOKUP($A17,Sheet3!$V:$V,Sheet3!$W:$W) | F17: CREDIT | G17: Blank | H17: =_xlfn.IFNA(_xlfn.XLOOKUP($A17,'T-00531'!$D:$D,'T-00531'!$E:$E),"Not in Sheet1") | J17: =_xlfn.XLOOKUP($A17,Sheet3!$P:$P,Sheet3!$Q:$Q) -> #N/A | L17: Always Blank for Debit,credit and Flexiti and gift card Redemption
A18: TNFMBR | B18: Customer/Mbr | C18: 8 | D18: High | E18: =_xlfn.XLOOKUP($A18,Sheet3!$V:$V,Sheet3!$W:$W) | F18: Blank | G18: 00000000 | H18: =_xlfn.IFNA(_xlfn.XLOOKUP($A18,'T-00531'!$D:$D,'T-00531'!$E:$E),"Not in Sheet1") | J18: =_xlfn.XLOOKUP($A18,Sheet3!$P:$P,Sheet3!$Q:$Q) -> #N/A | K18: N/A | L18: Always blank
A19: TNFSTS | B19: Status - A=ACTIVE; D=DELE | C19: 1 | E19: =_xlfn.XLOOKUP($A19,Sheet3!$V:$V,Sheet3!$W:$W) | F19: Blank | H19: =_xlfn.IFNA(_xlfn.XLOOKUP($A19,'T-00531'!$D:$D,'T-00531'!$E:$E),"Not in Sheet1") | J19: =_xlfn.XLOOKUP($A19,Sheet3!$P:$P,Sheet3!$Q:$Q) -> #N/A | K19: N/A | L19: Always blank
A20: TNFESI | B20: Employee Sale ID | C20: 5 | E20: =_xlfn.XLOOKUP($A20,Sheet3!$V:$V,Sheet3!$W:$W) | F20: Blank | H20: =_xlfn.IFNA(_xlfn.XLOOKUP($A20,'T-00531'!$D:$D,'T-00531'!$E:$E),"Not in Sheet1") | J20: =_xlfn.XLOOKUP($A20,Sheet3!$P:$P,Sheet3!$Q:$Q) -> #N/A | K20: N/A | L20: Calculated field set to '#####' for all employee sale i.e.TNFTTP = '04' Default to Blank
A21: TNFZIP | B21: Postal Code | C21: 10 | E21: =_xlfn.XLOOKUP($A21,Sheet3!$V:$V,Sheet3!$W:$W) | F21: Blank | H21: =_xlfn.IFNA(_xlfn.XLOOKUP($A21,'T-00531'!$D:$D,'T-00531'!$E:$E),"Not in Sheet1") | J21: =_xlfn.XLOOKUP($A21,Sheet3!$P:$P,Sheet3!$Q:$Q) -> #N/A | K21: N/A | L21: Always blank
A22: TNFMSR | B22: Mag Stripe Flag | C22: 1 | D22: Critical | E22: =_xlfn.XLOOKUP($A22,Sheet3!$V:$V,Sheet3!$W:$W) -> S | F22: Blank | G22: t | H22: =_xlfn.IFNA(_xlfn.XLOOKUP($A22,'T-00531'!$D:$D,'T-00531'!$E:$E),"Not in Sheet1") -> S | J22: =_xlfn.XLOOKUP($A22,Sheet3!$P:$P,Sheet3!$Q:$Q) -> #N/A | K22: ORAE.Transaction.Tenders[n].card.emv.tags.magStrip | L22: Mapping
A23: TNFEML | B23: eReceipt email | C23: 60 | E23: =_xlfn.XLOOKUP($A23,Sheet3!$V:$V,Sheet3!$W:$W) | F23: Blank | H23: =_xlfn.IFNA(_xlfn.XLOOKUP($A23,'T-00531'!$D:$D,'T-00531'!$E:$E),"Not in Sheet1") | J23: =_xlfn.XLOOKUP($A23,Sheet3!$P:$P,Sheet3!$Q:$Q) -> #N/A | L23: Always blank
A24: TNFHSH | B24: Payment Hash Value | C24: 64 | E24: =_xlfn.XLOOKUP($A24,Sheet3!$V:$V,Sheet3!$W:$W) | F24: Blank | H24: =_xlfn.IFNA(_xlfn.XLOOKUP($A24,'T-00531'!$D:$D,'T-00531'!$E:$E),"Not in Sheet1") | J24: =_xlfn.XLOOKUP($A24,Sheet3!$P:$P,Sheet3!$Q:$Q) -> #N/A | K24: N/A | L24: Always blank
A25: TNFPLC | B25: Polled Store | C25: 5 | E25: =_xlfn.XLOOKUP($A25,Sheet3!$V:$V,Sheet3!$W:$W) -> 55010 | F25: 83010 | H25: =_xlfn.IFNA(_xlfn.XLOOKUP($A25,'T-00531'!$D:$D,'T-00531'!$E:$E),"Not in Sheet1") -> 55010 | J25: =_xlfn.XLOOKUP($A25,Sheet3!$P:$P,Sheet3!$Q:$Q) -> #N/A | K25: BusinessContext.Store.StoreID | L25: Mapping
A26: TNFPCN | B26: Poll Cen | C26: 1 | E26: =_xlfn.XLOOKUP($A26,Sheet3!$V:$V,Sheet3!$W:$W) -> 1 | F26: 1 | H26: =_xlfn.IFNA(_xlfn.XLOOKUP($A26,'T-00531'!$D:$D,'T-00531'!$E:$E),"Not in Sheet1") -> 1 | J26: =_xlfn.XLOOKUP($A26,Sheet3!$P:$P,Sheet3!$Q:$Q) -> #N/A | K26: N/A | L26: 1
A27: TNFPDT | B27: Poll Date | C27: 6 | E27: =_xlfn.XLOOKUP($A27,Sheet3!$V:$V,Sheet3!$W:$W) -> 260128 | F27: 260122 | H27: =_xlfn.IFNA(_xlfn.XLOOKUP($A27,'T-00531'!$D:$D,'T-00531'!$E:$E),"Not in Sheet1") -> 260123 | J27: =_xlfn.XLOOKUP($A27,Sheet3!$P:$P,Sheet3!$Q:$Q) -> #N/A | K27: occurredAt (Provide a list of stores and MMS regions) | L27: Calculated Field based MMS Region occurredAt": "2026-01-13T17:00:53Z", YYMMDD "West - 8 Rest (ON&QC) -5"
A28: TNFCCN | B28: Create Cen | C28: 1 | E28: =_xlfn.XLOOKUP($A28,Sheet3!$V:$V,Sheet3!$W:$W) -> 1 | F28: 1 | H28: =_xlfn.IFNA(_xlfn.XLOOKUP($A28,'T-00531'!$D:$D,'T-00531'!$E:$E),"Not in Sheet1") -> 1 | J28: =_xlfn.XLOOKUP($A28,Sheet3!$P:$P,Sheet3!$Q:$Q) -> #N/A | K28: N/A | L28: 1
A29: TNFCDT | B29: Create Date | C29: 6 | E29: =_xlfn.XLOOKUP($A29,Sheet3!$V:$V,Sheet3!$W:$W) -> 260128 | F29: 260122 | H29: =_xlfn.IFNA(_xlfn.XLOOKUP($A29,'T-00531'!$D:$D,'T-00531'!$E:$E),"Not in Sheet1") -> 260123 | J29: =_xlfn.XLOOKUP($A29,Sheet3!$P:$P,Sheet3!$Q:$Q) -> #N/A | K29: occurredAt (Provide a list of stores and MMS regions) | L29: Calculated Field based MMS Region occurredAt": "2026-01-13T17:00:53Z", YYMMDD "West - 8 Rest (ON&QC) -5"
A30: TNFCTM | B30: Create Time | C30: 6 | E30: =_xlfn.XLOOKUP($A30,Sheet3!$V:$V,Sheet3!$W:$W) -> 144416 | F30: 75002 | H30: =_xlfn.IFNA(_xlfn.XLOOKUP($A30,'T-00531'!$D:$D,'T-00531'!$E:$E),"Not in Sheet1") -> 154417 | J30: =_xlfn.XLOOKUP($A30,Sheet3!$P:$P,Sheet3!$Q:$Q) -> #N/A | K30: occurredAt (Provide a list of stores and MMS regions) | L30: Calculated Field based MMS Region occurredAt": "2026-01-13T17:00:53Z", "West - 8 Rest (ON&QC) -5" HHMMSS
A31: ATFSST | B31: Sales Store | C31: 5 | E31: =_xlfn.XLOOKUP($A31,Sheet3!$V:$V,Sheet3!$W:$W) -> 0 | F31: 0 | H31: =_xlfn.IFNA(_xlfn.XLOOKUP($A31,'T-00531'!$D:$D,'T-00531'!$E:$E),"Not in Sheet1") -> 0 | J31: =_xlfn.XLOOKUP($A31,Sheet3!$P:$P,Sheet3!$Q:$Q) -> #N/A | K31: N/A | L31: always 0
A32: ATFIST | B32: Inv. Store | C32: 5 | E32: =_xlfn.XLOOKUP($A32,Sheet3!$V:$V,Sheet3!$W:$W) -> 0 | F32: 0 | H32: =_xlfn.IFNA(_xlfn.XLOOKUP($A32,'T-00531'!$D:$D,'T-00531'!$E:$E),"Not in Sheet1") -> 0 | J32: =_xlfn.XLOOKUP($A32,Sheet3!$P:$P,Sheet3!$Q:$Q) -> #N/A | K32: N/A | L32: always 0
A33: ATFOTX | B33: Original Trans# | C33: 5 | E33: =_xlfn.XLOOKUP($A33,Sheet3!$V:$V,Sheet3!$W:$W) | F33: Blank | H33: =_xlfn.IFNA(_xlfn.XLOOKUP($A33,'T-00531'!$D:$D,'T-00531'!$E:$E),"Not in Sheet1") | J33: =_xlfn.XLOOKUP($A33,Sheet3!$P:$P,Sheet3!$Q:$Q) -> #N/A | K33: N/A | L33: always blank
A34: ATFMBT | B34: Customer Type | C34: 1 | E34: =_xlfn.XLOOKUP($A34,Sheet3!$V:$V,Sheet3!$W:$W) | F34: Blank | H34: =_xlfn.IFNA(_xlfn.XLOOKUP($A34,'T-00531'!$D:$D,'T-00531'!$E:$E),"Not in Sheet1") | J34: =_xlfn.XLOOKUP($A34,Sheet3!$P:$P,Sheet3!$Q:$Q) -> #N/A | K34: N/A | L34: always blank
A35: ATFORD | B35: Order Number | C35: 8 | E35: =_xlfn.XLOOKUP($A35,Sheet3!$V:$V,Sheet3!$W:$W) | F35: Blank | H35: =_xlfn.IFNA(_xlfn.XLOOKUP($A35,'T-00531'!$D:$D,'T-00531'!$E:$E),"Not in Sheet1") | J35: =_xlfn.XLOOKUP($A35,Sheet3!$P:$P,Sheet3!$Q:$Q) -> #N/A | K35: N/A | L35: always blank
A36: ATFPRO | B36: Project Number | C36: 5 | E36: =_xlfn.XLOOKUP($A36,Sheet3!$V:$V,Sheet3!$W:$W) | F36: Blank | H36: =_xlfn.IFNA(_xlfn.XLOOKUP($A36,'T-00531'!$D:$D,'T-00531'!$E:$E),"Not in Sheet1") | J36: =_xlfn.XLOOKUP($A36,Sheet3!$P:$P,Sheet3!$Q:$Q) -> #N/A | K36: N/A | L36: always blank
J37: =_xlfn.XLOOKUP($A37,Sheet3!$P:$P,Sheet3!$Q:$Q) -> 0

Sheet T-00531
A2: TNFTTP: "01", | B2: =SUBSTITUTE(SUBSTITUTE(A2,"""",""),",","") -> TNFTTP: 01 | C2: =_xlfn.TEXTBEFORE(B2,":") -> TNFTTP | D2: =SUBSTITUTE(TRIM(C2)," ","") -> TNFTTP | E2: =_xlfn.TEXTAFTER(B2,":") -> 01 | G2: =COUNTIF('T-00531'!D:D,A2) -> 0
A3: "TNFTDT": "260123", | B3: =SUBSTITUTE(SUBSTITUTE(A3,"""",""),",","") -> TNFTDT: 260123 | C3: =_xlfn.TEXTBEFORE(B3,":") -> TNFTDT | D3: =SUBSTITUTE(TRIM(C3)," ","") -> TNFTDT | E3: =_xlfn.TEXTAFTER(B3,":") -> 260123 | G3: =COUNTIF('T-00531'!D:D,A3) -> 0
A4: "TNFTTM": "154417", | B4: =SUBSTITUTE(SUBSTITUTE(A4,"""",""),",","") -> TNFTTM: 154417 | C4: =_xlfn.TEXTBEFORE(B4,":") -> TNFTTM | D4: =SUBSTITUTE(TRIM(C4)," ","") -> TNFTTM | E4: =_xlfn.TEXTAFTER(B4,":") -> 154417 | G4: =COUNTIF('T-00531'!D:D,A4) -> 0
A5: "TNFCLK": "00085", | B5: =SUBSTITUTE(SUBSTITUTE(A5,"""",""),",","") -> TNFCLK: 00085 | C5: =_xlfn.TEXTBEFORE(B5,":") -> TNFCLK | D5: =SUBSTITUTE(TRIM(C5)," ","") -> TNFCLK | E5: =_xlfn.TEXTAFTER(B5,":") -> 00085 | G5: =COUNTIF('T-00531'!D:D,A5) -> 0
A6: "TNFREG": "085", | B6: =SUBSTITUTE(SUBSTITUTE(A6,"""",""),",","") -> TNFREG: 085 | C6: =_xlfn.TEXTBEFORE(B6,":") -> TNFREG | D6: =SUBSTITUTE(TRIM(C6)," ","") -> TNFREG | E6: =_xlfn.TEXTAFTER(B6,":") -> 085 | G6: =COUNTIF('T-00531'!D:D,A6) -> 0
A7: "TNFTTX": "00531", | B7: =SUBSTITUTE(SUBSTITUTE(A7,"""",""),",","") -> TNFTTX: 00531 | C7: =_xlfn.TEXTBEFORE(B7,":") -> TNFTTX | D7: =SUBSTITUTE(TRIM(C7)," ","") -> TNFTTX | E7: =_xlfn.TEXTAFTER(B7,":") -> 00531 | G7: =COUNTIF('T-00531'!D:D,A7) -> 0
A8: "TNFTSQ": "00005", | B8: =SUBSTITUTE(SUBSTITUTE(A8,"""",""),",","") -> TNFTSQ: 00005 | C8: =_xlfn.TEXTBEFORE(B8,":") -> TNFTSQ | D8: =SUBSTITUTE(TRIM(C8)," ","") -> TNFTSQ | E8: =_xlfn.TEXTAFTER(B8,":") -> 00005 | G8: =COUNTIF('T-00531'!D:D,A8) -> 0
A9: "TNFFCD": "VI", | B9: =SUBSTITUTE(SUBSTITUTE(A9,"""",""),",","") -> TNFFCD: VI | C9: =_xlfn.TEXTBEFORE(B9,":") -> TNFFCD | D9: =SUBSTITUTE(TRIM(C9)," ","") -> TNFFCD | E9: =_xlfn.TEXTAFTER(B9,":") -> VI
A10: "TNFAMT": "00000002586", | B10: =SUBSTITUTE(SUBSTITUTE(A10,"""",""),",","") -> TNFAMT: 00000002586 | C10: =_xlfn.TEXTBEFORE(B10,":") -> TNFAMT | D10: =SUBSTITUTE(TRIM(C10)," ","") -> TNFAMT | E10: =_xlfn.TEXTAFTER(B10,":") -> 00000002586
A11: "TNFAMN": "", | B11: =SUBSTITUTE(SUBSTITUTE(A11,"""",""),",","") -> TNFAMN: | C11: =_xlfn.TEXTBEFORE(B11,":") -> TNFAMN | D11: =SUBSTITUTE(TRIM(C11)," ","") -> TNFAMN | E11: =_xlfn.TEXTAFTER(B11,":")
A12: "TNFCCD": "***************4903", | B12: =SUBSTITUTE(SUBSTITUTE(A12,"""",""),",","") -> TNFCCD: ***************4903 | C12: =_xlfn.TEXTBEFORE(B12,":") -> TNFCCD | D12: =SUBSTITUTE(TRIM(C12)," ","") -> TNFCCD | E12: =_xlfn.TEXTAFTER(B12,":") -> ***************4903
A13: "TNFEXP": "0000", | B13: =SUBSTITUTE(SUBSTITUTE(A13,"""",""),",","") -> TNFEXP: 0000 | C13: =_xlfn.TEXTBEFORE(B13,":") -> TNFEXP | D13: =SUBSTITUTE(TRIM(C13)," ","") -> TNFEXP | E13: =_xlfn.TEXTAFTER(B13,":") -> 0000
A14: "TNFAUT": "066851", | B14: =SUBSTITUTE(SUBSTITUTE(A14,"""",""),",","") -> TNFAUT: 066851 | C14: =_xlfn.TEXTBEFORE(B14,":") -> TNFAUT | D14: =SUBSTITUTE(TRIM(C14)," ","") -> TNFAUT | E14: =_xlfn.TEXTAFTER(B14,":") -> 066851
A15: "TNFRFC": "", | B15: =SUBSTITUTE(SUBSTITUTE(A15,"""",""),",","") -> TNFRFC: | C15: =_xlfn.TEXTBEFORE(B15,":") -> TNFRFC | D15: =SUBSTITUTE(TRIM(C15)," ","") -> TNFRFC | E15: =_xlfn.TEXTAFTER(B15,":")
A16: "TNFRDS": "", | B16: =SUBSTITUTE(SUBSTITUTE(A16,"""",""),",","") -> TNFRDS: | C16: =_xlfn.TEXTBEFORE(B16,":") -> TNFRDS | D16: =SUBSTITUTE(TRIM(C16)," ","") -> TNFRDS | E16: =_xlfn.TEXTAFTER(B16,":")
A17: "TNFMBR": "", | B17: =SUBSTITUTE(SUBSTITUTE(A17,"""",""),",","") -> TNFMBR: | C17: =_xlfn.TEXTBEFORE(B17,":") -> TNFMBR | D17: =SUBSTITUTE(TRIM(C17)," ","") -> TNFMBR | E17: =_xlfn.TEXTAFTER(B17,":")
A18: "TNFSTS": " ", | B18: =SUBSTITUTE(SUBSTITUTE(A18,"""",""),",","") -> TNFSTS: | C18: =_xlfn.TEXTBEFORE(B18,":") -> TNFSTS | D18: =SUBSTITUTE(TRIM(C18)," ","") -> TNFSTS | E18: =_xlfn.TEXTAFTER(B18,":")
A19: "TNFESI": "", | B19: =SUBSTITUTE(SUBSTITUTE(A19,"""",""),",","") -> TNFESI: | C19: =_xlfn.TEXTBEFORE(B19,":") -> TNFESI | D19: =SUBSTITUTE(TRIM(C19)," ","") -> TNFESI | E19: =_xlfn.TEXTAFTER(B19,":") | G19: {=x} -> #NAME?
A20: "TNFZIP": "", | B20: =SUBSTITUTE(SUBSTITUTE(A20,"""",""),",","") -> TNFZIP: | C20: =_xlfn.TEXTBEFORE(B20,":") -> TNFZIP | D20: =SUBSTITUTE(TRIM(C20)," ","") -> TNFZIP | E20: =_xlfn.TEXTAFTER(B20,":")
A21: "TNFMSR": "S", | B21: =SUBSTITUTE(SUBSTITUTE(A21,"""",""),",","") -> TNFMSR: S | C21: =_xlfn.TEXTBEFORE(B21,":") -> TNFMSR | D21: =SUBSTITUTE(TRIM(C21)," ","") -> TNFMSR | E21: =_xlfn.TEXTAFTER(B21,":") -> S
A22: "TNFEML": "", | B22: =SUBSTITUTE(SUBSTITUTE(A22,"""",""),",","") -> TNFEML: | C22: =_xlfn.TEXTBEFORE(B22,":") -> TNFEML | D22: =SUBSTITUTE(TRIM(C22)," ","") -> TNFEML | E22: =_xlfn.TEXTAFTER(B22,":")
A23: "TNFHSH": "", | B23: =SUBSTITUTE(SUBSTITUTE(A23,"""",""),",","") -> TNFHSH: | C23: =_xlfn.TEXTBEFORE(B23,":") -> TNFHSH | D23: =SUBSTITUTE(TRIM(C23)," ","") -> TNFHSH | E23: =_xlfn.TEXTAFTER(B23,":")
A24: "TNFPLC": 55010, | B24: =SUBSTITUTE(SUBSTITUTE(A24,"""",""),",","") -> TNFPLC: 55010 | C24: =_xlfn.TEXTBEFORE(B24,":") -> TNFPLC | D24: =SUBSTITUTE(TRIM(C24)," ","") -> TNFPLC | E24: =_xlfn.TEXTAFTER(B24,":") -> 55010
A25: "TNFPCN": 1, | B25: =SUBSTITUTE(SUBSTITUTE(A25,"""",""),",","") -> TNFPCN: 1 | C25: =_xlfn.TEXTBEFORE(B25,":") -> TNFPCN | D25: =SUBSTITUTE(TRIM(C25)," ","") -> TNFPCN | E25: =_xlfn.TEXTAFTER(B25,":") -> 1
A26: "TNFPDT": 260123, | B26: =SUBSTITUTE(SUBSTITUTE(A26,"""",""),",","") -> TNFPDT: 260123 | C26: =_xlfn.TEXTBEFORE(B26,":") -> TNFPDT | D26: =SUBSTITUTE(TRIM(C26)," ","") -> TNFPDT | E26: =_xlfn.TEXTAFTER(B26,":") -> 260123
A27: "TNFCCN": 1, | B27: =SUBSTITUTE(SUBSTITUTE(A27,"""",""),",","") -> TNFCCN: 1 | C27: =_xlfn.TEXTBEFORE(B27,":") -> TNFCCN | D27: =SUBSTITUTE(TRIM(C27)," ","") -> TNFCCN | E27: =_xlfn.TEXTAFTER(B27,":") -> 1
A28: "TNFCDT": 260123, | B28: =SUBSTITUTE(SUBSTITUTE(A28,"""",""),",","") -> TNFCDT: 260123 | C28: =_xlfn.TEXTBEFORE(B28,":") -> TNFCDT | D28: =SUBSTITUTE(TRIM(C28)," ","") -> TNFCDT | E28: =_xlfn.TEXTAFTER(B28,":") -> 260123
A29: "TNFCTM": 154417, | B29: =SUBSTITUTE(SUBSTITUTE(A29,"""",""),",","") -> TNFCTM: 154417 | C29: =_xlfn.TEXTBEFORE(B29,":") -> TNFCTM | D29: =SUBSTITUTE(TRIM(C29)," ","") -> TNFCTM | E29: =_xlfn.TEXTAFTER(B29,":") -> 154417
A30: "ATFSST": 0, | B30: =SUBSTITUTE(SUBSTITUTE(A30,"""",""),",","") -> ATFSST: 0 | C30: =_xlfn.TEXTBEFORE(B30,":") -> ATFSST | D30: =SUBSTITUTE(TRIM(C30)," ","") -> ATFSST | E30: =_xlfn.TEXTAFTER(B30,":") -> 0
A31: "ATFIST": 0, | B31: =SUBSTITUTE(SUBSTITUTE(A31,"""",""),",","") -> ATFIST: 0 | C31: =_xlfn.TEXTBEFORE(B31,":") -> ATFIST | D31: =SUBSTITUTE(TRIM(C31)," ","") -> ATFIST | E31: =_xlfn.TEXTAFTER(B31,":") -> 0
... A35: "ATFPRO": "" | B35: =SUBSTITUTE(SUBSTITUTE(A35,"""",""),",","") -> ATFPRO: | C35: =_xlfn.TEXTBEFORE(B35,":") -> ATFPRO | D35: =SUBSTITUTE(TRIM(C35)," ","") -> ATFPRO | E35: =_xlfn.TEXTAFTER(B35,":")

Sheet Sheet1
A2: "SLFTTP": "01", | B2: =TRIM( SUBSTITUTE( SUBSTITUTE( LEFT(A2, FIND(":", A2) - 1), """", "" ), ",", "" ) ) -> SLFTTP | C2: =TRIM( SUBSTITUTE( SUBSTITUTE( _xlfn.TEXTAFTER(A2, ":"), """", "" ), ",", "" ) ) -> 01 | D2: =B2 -> SLFTTP | E2: =C2 -> 01 | H2: "SLFTTP": "01", | I2: =TRIM( SUBSTITUTE( SUBSTITUTE( LEFT(H2, FIND(":", H2) - 1), """", "" ), ",", "" ) ) -> SLFTTP | J2: =TRIM( SUBSTITUTE( SUBSTITUTE( _xlfn.TEXTAFTER(H2, ":"), """", "" ), ",", "" ) ) -> 01 | K2: =I2 -> SLFTTP | L2: =J2 -> 01
A3: "SLFLNT": "01", | B3: =TRIM( SUBSTITUTE( SUBSTITUTE( LEFT(A3, FIND(":", A3) - 1), """", "" ), ",", "" ) ) -> SLFLNT | C3: =TRIM( SUBSTITUTE( SUBSTITUTE( _xlfn.TEXTAFTER(A3, ":"), """", "" ), ",", "" ) ) -> 01 | D3: =B3 -> SLFLNT | E3: =C3 -> 01 | H3: "SLFLNT": "01", | I3: =TRIM( SUBSTITUTE( SUBSTITUTE( LEFT(H3, FIND(":", H3) - 1), """", "" ), ",", "" ) ) -> SLFLNT | J3: =TRIM( SUBSTITUTE( SUBSTITUTE( _xlfn.TEXTAFTER(H3, ":"), """", "" ), ",", "" ) ) -> 01 | K3: =I3 -> SLFLNT | L3: =J3 -> 01
A4: "SLFTDT": "260123", | B4: =TRIM( SUBSTITUTE( SUBSTITUTE( LEFT(A4, FIND(":", A4) - 1), """", "" ), ",", "" ) ) -> SLFTDT | C4: =TRIM( SUBSTITUTE( SUBSTITUTE( _xlfn.TEXTAFTER(A4, ":"), """", "" ), ",", "" ) ) -> 260123 | D4: =B4 -> SLFTDT | E4: =C4 -> 260123 | H4: "SLFTDT": "260123", | I4: =TRIM( SUBSTITUTE( SUBSTITUTE( LEFT(H4, FIND(":", H4) - 1), """", "" ), ",", "" ) ) -> SLFTDT | J4: =TRIM( SUBSTITUTE( SUBSTITUTE( _xlfn.TEXTAFTER(H4, ":"), """", "" ), ",", "" ) ) -> 260123 | K4: =I4 -> SLFTDT | L4: =J4 -> 260123
A5: "SLFTTM": "154417", | B5: =TRIM( SUBSTITUTE( SUBSTITUTE( LEFT(A5, FIND(":", A5) - 1), """", "" ), ",", "" ) ) -> SLFTTM | C5: =TRIM( SUBSTITUTE( SUBSTITUTE( _xlfn.TEXTAFTER(A5, ":"), """", "" ), ",", "" ) ) -> 154417 | D5: =B5 -> SLFTTM | E5: =C5 -> 154417 | H5: "SLFTTM": "154417", | I5: =TRIM( SUBSTITUTE( SUBSTITUTE( LEFT(H5, FIND(":", H5) - 1), """", "" ), ",", "" ) ) -> SLFTTM | J5: =TRIM( SUBSTITUTE( SUBSTITUTE( _xlfn.TEXTAFTER(H5, ":"), """", "" ), ",", "" ) ) -> 154417 | K5: =I5 -> SLFTTM | L5: =J5 -> 154417
A6: "SLFCLK": "00085", | B6: =TRIM( SUBSTITUTE( SUBSTITUTE( LEFT(A6, FIND(":", A6) - 1), """", "" ), ",", "" ) ) -> SLFCLK | C6: =TRIM( SUBSTITUTE( SUBSTITUTE( _xlfn.TEXTAFTER(A6, ":"), """", "" ), ",", "" ) ) -> 00085 | D6: =B6 -> SLFCLK | E6: =C6 -> 00085 | H6: "SLFCLK": "00085", | I6: =TRIM( SUBSTITUTE( SUBSTITUTE( LEFT(H6, FIND(":", H6) - 1), """", "" ), ",", "" ) ) -> SLFCLK | J6: =TRIM( SUBSTITUTE( SUBSTITUTE( _xlfn.TEXTAFTER(H6, ":"), """", "" ), ",", "" ) ) -> 00085 | K6: =I6 -> SLFCLK | L6: =J6 -> 00085
A7: "SLFREG": "085", | B7: =TRIM( SUBSTITUTE( SUBSTITUTE( LEFT(A7, FIND(":", A7) - 1), """", "" ), ",", "" ) ) -> SLFREG | C7: =TRIM( SUBSTITUTE( SUBSTITUTE( _xlfn.TEXTAFTER(A7, ":"), """", "" ), ",", "" ) ) -> 085 | D7: =B7 -> SLFREG | E7: =C7 -> 085 | H7: "SLFREG": "085", | I7: =TRIM( SUBSTITUTE( SUBSTITUTE( LEFT(H7, FIND(":", H7) - 1), """", "" ), ",", "" ) ) -> SLFREG | J7: =TRIM( SUBSTITUTE( SUBSTITUTE( _xlfn.TEXTAFTER(H7, ":"), """", "" ), ",", "" ) ) -> 085 | K7: =I7 -> SLFREG | L7: =J7 -> 085
A8: "SLFTTX": "00531", | B8: =TRIM( SUBSTITUTE( SUBSTITUTE( LEFT(A8, FIND(":", A8) - 1), """", "" ), ",", "" ) ) -> SLFTTX | C8: =TRIM( SUBSTITUTE( SUBSTITUTE( _xlfn.TEXTAFTER(A8, ":"), """", "" ), ",", "" ) ) -> 00531 | D8: =B8 -> SLFTTX | E8: =C8 -> 00531 | H8: "SLFTTX": "00531", | I8: =TRIM( SUBSTITUTE( SUBSTITUTE( LEFT(H8, FIND(":", H8) - 1), """", "" ), ",", "" ) ) -> SLFTTX | J8: =TRIM( SUBSTITUTE( SUBSTITUTE( _xlfn.TEXTAFTER(H8, ":"), """", "" ), ",", "" ) ) -> 00531 | K8: =I8 -> SLFTTX | L8: =J8 -> 00531
A9: "SLFTSQ": "00001", | B9: =TRIM( SUBSTITUTE( SUBSTITUTE( LEFT(A9, FIND(":", A9) - 1), """", "" ), ",", "" ) ) -> SLFTSQ | C9: =TRIM( SUBSTITUTE( SUBSTITUTE( _xlfn.TEXTAFTER(A9, ":"), """", "" ), ",", "" ) ) -> 00001 | D9: =B9 -> SLFTSQ | E9: =C9 -> 00001 | H9: "SLFTSQ": "00002", | I9: =TRIM( SUBSTITUTE( SUBSTITUTE( LEFT(H9, FIND(":", H9) - 1), """", "" ), ",", "" ) ) -> SLFTSQ | J9: =TRIM( SUBSTITUTE( SUBSTITUTE( _xlfn.TEXTAFTER(H9, ":"), """", "" ), ",", "" ) ) -> 00002 | K9: =I9 -> SLFTSQ | L9: =J9 -> 00002
A10: "SLFSKU": "000334898", | B10: =TRIM( SUBSTITUTE( SUBSTITUTE( LEFT(A10, FIND(":", A10) - 1), """", "" ), ",", "" ) ) -> SLFSKU | C10: =TRIM( SUBSTITUTE( SUBSTITUTE( _xlfn.TEXTAFTER(A10, ":"), """", "" ), ",", "" ) ) -> 000334898 | D10: =B10 -> SLFSKU | E10: =C10 -> 000334898 | H10: "SLFSKU": "000169577", | I10: =TRIM( SUBSTITUTE( SUBSTITUTE( LEFT(H10, FIND(":", H10) - 1), """", "" ), ",", "" ) ) -> SLFSKU | J10: =TRIM( SUBSTITUTE( SUBSTITUTE( _xlfn.TEXTAFTER(H10, ":"), """", "" ), ",", "" ) ) -> 000169577 | K10: =I10 -> SLFSKU | L10: =J10 -> 000169577
A11: "SLFQTY": "000000100", | B11: =TRIM( SUBSTITUTE( SUBSTITUTE( LEFT(A11, FIND(":", A11) - 1), """", "" ), ",", "" ) ) -> SLFQTY | C11: =TRIM( SUBSTITUTE( SUBSTITUTE( _xlfn.TEXTAFTER(A11, ":"), """", "" ), ",", "" ) ) -> 000000100 | D11: =B11 -> SLFQTY | E11: =C11 -> 000000100 | H11: "SLFQTY": "000000100", | I11: =TRIM( SUBSTITUTE( SUBSTITUTE( LEFT(H11, FIND(":", H11) - 1), """", "" ), ",", "" ) ) -> SLFQTY | J11: =TRIM( SUBSTITUTE( SUBSTITUTE( _xlfn.TEXTAFTER(H11, ":"), """", "" ), ",", "" ) ) -> 000000100 | K11: =I11 -> SLFQTY | L11: =J11 -> 000000100
A12: "SLFQTN": "", | B12: =TRIM( SUBSTITUTE( SUBSTITUTE( LEFT(A12, FIND(":", A12) - 1), """", "" ), ",", "" ) ) -> SLFQTN | C12: =TRIM( SUBSTITUTE( SUBSTITUTE( _xlfn.TEXTAFTER(A12, ":"), """", "" ), ",", "" ) ) | D12: =B12 -> SLFQTN | E12: =C12 | H12: "SLFQTN": "", | I12: =TRIM( SUBSTITUTE( SUBSTITUTE( LEFT(H12, FIND(":", H12) - 1), """", "" ), ",", "" ) ) -> SLFQTN | J12: =TRIM( SUBSTITUTE( SUBSTITUTE( _xlfn.TEXTAFTER(H12, ":"), """", "" ), ",", "" ) ) | K12: =I12 -> SLFQTN | L12: =J12
A13: "SLFORG": "000001129", | B13: =TRIM( SUBSTITUTE( SUBSTITUTE( LEFT(A13, FIND(":", A13) - 1), """", "" ), ",", "" ) ) -> SLFORG | C13: =TRIM( SUBSTITUTE( SUBSTITUTE( _xlfn.TEXTAFTER(A13, ":"), """", "" ), ",", "" ) ) -> 000001129 | D13: =B13 -> SLFORG | E13: =C13 -> 000001129 | H13: "SLFORG": "000001159", | I13: =TRIM( SUBSTITUTE( SUBSTITUTE( LEFT(H13, FIND(":", H13) - 1), """", "" ), ",", "" ) ) -> SLFORG | J13: =TRIM( SUBSTITUTE( SUBSTITUTE( _xlfn.TEXTAFTER(H13, ":"), """", "" ), ",", "" ) ) -> 000001159 | K13: =I13 -> SLFORG | L13: =J13 -> 000001159
... A71: "SLFECN": 0 | B71: =TRIM( SUBSTITUTE( SUBSTITUTE( LEFT(A71, FIND(":", A71) - 1), """", "" ), ",", "" ) ) -> SLFECN | C71: =TRIM( SUBSTITUTE( SUBSTITUTE( _xlfn.TEXTAFTER(A71, ":"), """", "" ), ",", "" ) ) -> 0 | D71: =B71 -> SLFECN | E71: =C71 -> 0 | H71: "SLFECN": 0 | I71: =TRIM( SUBSTITUTE( SUBSTITUTE( LEFT(H71, FIND(":", H71) - 1), """", "" ), ",", "" ) ) -> SLFECN | J71: =TRIM( SUBSTITUTE( SUBSTITUTE( _xlfn.TEXTAFTER(H71, ":"), """", "" ), ",", "" ) ) -> 0 | K71: =I71 -> SLFECN | L71: =J71 -> 0

Sheet Sheet2
A1: SKU 1 | G1: SKU 2 | M1: SKU 3 | S1: SKU 4 | Y1: Tax 1 | AE1: Tender1
A3: "SLFTTP": "01", | B3: =TRIM( SUBSTITUTE( SUBSTITUTE( LEFT(A3, FIND(":", A3) - 1), """", "" ), ",", "" ) ) -> SLFTTP | C3: =TRIM( SUBSTITUTE( SUBSTITUTE( _xlfn.TEXTAFTER(A3, ":"), """", "" ), ",", "" ) ) -> 01 | D3: =B3 -> SLFTTP | E3: =C3 -> 01 | G3: SLFTTP: "01", | H3: =TRIM( SUBSTITUTE( SUBSTITUTE( LEFT(G3, FIND(":", G3) - 1), """", "" ), ",", "" ) ) -> SLFTTP | I3: =TRIM( SUBSTITUTE( SUBSTITUTE( _xlfn.TEXTAFTER(G3, ":"), """", "" ), ",", "" ) ) -> 01 | J3: =H3 -> SLFTTP | K3: =I3 -> 01 | M3: SLFTTP: "01", | N3: =TRIM( SUBSTITUTE( SUBSTITUTE( LEFT(M3, FIND(":", M3) - 1), """", "" ), ",", "" ) ) -> SLFTTP | O3: =TRIM( SUBSTITUTE( SUBSTITUTE( _xlfn.TEXTAFTER(M3, ":"), """", "" ), ",", "" ) ) -> 01 | P3: =N3 -> SLFTTP | Q3: =O3 -> 01 | S3: SLFTTP: "01", | T3: =TRIM( SUBSTITUTE( SUBSTITUTE( LEFT(S3, FIND(":", S3) - 1), """", "" ), ",", "" ) ) -> SLFTTP | U3: =TRIM( SUBSTITUTE( SUBSTITUTE( _xlfn.TEXTAFTER(S3, ":"), """", "" ), ",", "" ) ) -> 01 | V3: =T3 -> SLFTTP | W3: =U3 -> 01 | Y3: SLFTTP: "01", | Z3: =TRIM( SUBSTITUTE( SUBSTITUTE( LEFT(Y3, FIND(":", Y3) - 1), """", "" ), ",", "" ) ) -> SLFTTP | AA3: =TRIM( SUBSTITUTE( SUBSTITUTE( _xlfn.TEXTAFTER(Y3, ":"), """", "" ), ",", "" ) ) -> 01 | AB3: =Z3 -> SLFTTP | AC3: =AA3 -> 01 | AE3: TNFTTP: "01", | AF3: =TRIM( SUBSTITUTE( SUBSTITUTE( LEFT(AE3, FIND(":", AE3) - 1), """", "" ), ",", "" ) ) -> TNFTTP | AG3: =TRIM( SUBSTITUTE( SUBSTITUTE( _xlfn.TEXTAFTER(AE3, ":"), """", "" ), ",", "" ) ) -> 01 | AH3: =AF3 -> TNFTTP | AI3: =AG3 -> 01
A4: "SLFLNT": "01", | B4: =TRIM( SUBSTITUTE( SUBSTITUTE( LEFT(A4, FIND(":", A4) - 1), """", "" ), ",", "" ) ) -> SLFLNT | C4: =TRIM( SUBSTITUTE( SUBSTITUTE( _xlfn.TEXTAFTER(A4, ":"), """", "" ), ",", "" ) ) -> 01 | D4: =B4 -> SLFLNT | E4: =C4 -> 01 | G4: "SLFLNT": "01", | H4: =TRIM( SUBSTITUTE( SUBSTITUTE( LEFT(G4, FIND(":", G4) - 1), """", "" ), ",", "" ) ) -> SLFLNT | I4: =TRIM( SUBSTITUTE( SUBSTITUTE( _xlfn.TEXTAFTER(G4, ":"), """", "" ), ",", "" ) ) -> 01 | J4: =H4 -> SLFLNT | K4: =I4 -> 01 | M4: "SLFLNT": "01", | N4: =TRIM( SUBSTITUTE( SUBSTITUTE( LEFT(M4, FIND(":", M4) - 1), """", "" ), ",", "" ) ) -> SLFLNT | O4: =TRIM( SUBSTITUTE( SUBSTITUTE( _xlfn.TEXTAFTER(M4, ":"), """", "" ), ",", "" ) ) -> 01 | P4: =N4 -> SLFLNT | Q4: =O4 -> 01 | S4: "SLFLNT": "01", | T4: =TRIM( SUBSTITUTE( SUBSTITUTE( LEFT(S4, FIND(":", S4) - 1), """", "" ), ",", "" ) ) -> SLFLNT | U4: =TRIM( SUBSTITUTE( SUBSTITUTE( _xlfn.TEXTAFTER(S4, ":"), """", "" ), ",", "" ) ) -> 01 | V4: =T4 -> SLFLNT | W4: =U4 -> 01 | Y4: "SLFLNT": "XH", | Z4: =TRIM( SUBSTITUTE( SUBSTITUTE( LEFT(Y4, FIND(":", Y4) - 1), """", "" ), ",", "" ) ) -> SLFLNT | AA4: =TRIM( SUBSTITUTE( SUBSTITUTE( _xlfn.TEXTAFTER(Y4, ":"), """", "" ), ",", "" ) ) -> XH | AB4: =Z4 -> SLFLNT | AC4: =AA4 -> XH | AE4: "TNFTDT": "260126", | AF4: =TRIM( SUBSTITUTE( SUBSTITUTE( LEFT(AE4, FIND(":", AE4) - 1), """", "" ), ",", "" ) ) -> TNFTDT | AG4: =TRIM( SUBSTITUTE( SUBSTITUTE( _xlfn.TEXTAFTER(AE4, ":"), """", "" ), ",", "" ) ) -> 260126 | AH4: =AF4 -> TNFTDT | AI4: =AG4 -> 260126
A5: "SLFTDT": "260126", | B5: =TRIM( SUBSTITUTE( SUBSTITUTE( LEFT(A5, FIND(":", A5) - 1), """", "" ), ",", "" ) ) -> SLFTDT | C5: =TRIM( SUBSTITUTE( SUBSTITUTE( _xlfn.TEXTAFTER(A5, ":"), """", "" ), ",", "" ) ) -> 260126 | D5: =B5 -> SLFTDT | E5: =C5 -> 260126 | G5: "SLFTDT": "260126", | H5: =TRIM( SUBSTITUTE( SUBSTITUTE( LEFT(G5, FIND(":", G5) - 1), """", "" ), ",", "" ) ) -> SLFTDT | I5: =TRIM( SUBSTITUTE( SUBSTITUTE( _xlfn.TEXTAFTER(G5, ":"), """", "" ), ",", "" ) ) -> 260126 | J5: =H5 -> SLFTDT | K5: =I5 -> 260126 | M5: "SLFTDT": "260126", | N5: =TRIM( SUBSTITUTE( SUBSTITUTE( LEFT(M5, FIND(":", M5) - 1), """", "" ), ",", "" ) ) -> SLFTDT | O5: =TRIM( SUBSTITUTE( SUBSTITUTE( _xlfn.TEXTAFTER(M5, ":"), """", "" ), ",", "" ) ) -> 260126 | P5: =N5 -> SLFTDT | Q5: =O5 -> 260126 | S5: "SLFTDT": "260126", | T5: =TRIM( SUBSTITUTE( SUBSTITUTE( LEFT(S5, FIND(":", S5) - 1), """", "" ), ",", "" ) ) -> SLFTDT | U5: =TRIM( SUBSTITUTE( SUBSTITUTE( _xlfn.TEXTAFTER(S5, ":"), """", "" ), ",", "" ) ) -> 260126 | V5: =T5 -> SLFTDT | W5: =U5 -> 260126 | Y5: "SLFTDT": "260126", | Z5: =TRIM( SUBSTITUTE( SUBSTITUTE( LEFT(Y5, FIND(":", Y5) - 1), """", "" ), ",", "" ) ) -> SLFTDT | AA5: =TRIM( SUBSTITUTE( SUBSTITUTE( _xlfn.TEXTAFTER(Y5, ":"), """", "" ), ",", "" ) ) -> 260126 | AB5: =Z5 -> SLFTDT | AC5: =AA5 -> 260126 | AE5: "TNFTTM": "163959", | AF5: =TRIM( SUBSTITUTE( SUBSTITUTE( LEFT(AE5, FIND(":", AE5) - 1), """", "" ), ",", "" ) ) -> TNFTTM | AG5: =TRIM( SUBSTITUTE( SUBSTITUTE( _xlfn.TEXTAFTER(AE5, ":"), """", "" ), ",", "" ) ) -> 163959 | AH5: =AF5 -> TNFTTM | AI5: =AG5 -> 163959
A6: "SLFTTM": "163959", | B6: =TRIM( SUBSTITUTE( SUBSTITUTE( LEFT(A6, FIND(":", A6) - 1), """", "" ), ",", "" ) ) -> SLFTTM | C6: =TRIM( SUBSTITUTE( SUBSTITUTE( _xlfn.TEXTAFTER(A6, ":"), """", "" ), ",", "" ) ) -> 163959 | D6: =B6 -> SLFTTM | E6: =C6 -> 163959 | G6: "SLFTTM": "163959", | H6: =TRIM( SUBSTITUTE( SUBSTITUTE( LEFT(G6, FIND(":", G6) - 1), """", "" ), ",", "" ) ) -> SLFTTM | I6: =TRIM( SUBSTITUTE( SUBSTITUTE( _xlfn.TEXTAFTER(G6, ":"), """", "" ), ",", "" ) ) -> 163959 | J6: =H6 -> SLFTTM | K6: =I6 -> 163959 | M6: "SLFTTM": "163959", | N6: =TRIM( SUBSTITUTE( SUBSTITUTE( LEFT(M6, FIND(":", M6) - 1), """", "" ), ",", "" ) ) -> SLFTTM | O6: =TRIM( SUBSTITUTE( SUBSTITUTE( _xlfn.TEXTAFTER(M6, ":"), """", "" ), ",", "" ) ) -> 163959 | P6: =N6 -> SLFTTM | Q6: =O6 -> 163959 | S6: "SLFTTM": "163959", | T6: =TRIM( SUBSTITUTE( SUBSTITUTE( LEFT(S6, FIND(":", S6) - 1), """", "" ), ",", "" ) ) -> SLFTTM | U6: =TRIM( SUBSTITUTE( SUBSTITUTE( _xlfn.TEXTAFTER(S6, ":"), """", "" ), ",", "" ) ) -> 163959 | V6: =T6 -> SLFTTM | W6: =U6 -> 163959 | Y6: "SLFTTM": "163959", | Z6: =TRIM( SUBSTITUTE( SUBSTITUTE( LEFT(Y6, FIND(":", Y6) - 1), """", "" ), ",", "" ) ) -> SLFTTM | AA6: =TRIM( SUBSTITUTE( SUBSTITUTE( _xlfn.TEXTAFTER(Y6, ":"), """", "" ), ",", "" ) ) -> 163959 | AB6: =Z6 -> SLFTTM | AC6: =AA6 -> 163959 | AE6: "TNFCLK": "00006", | AF6: =TRIM( SUBSTITUTE( SUBSTITUTE( LEFT(AE6, FIND(":", AE6) - 1), """", "" ), ",", "" ) ) -> TNFCLK | AG6: =TRIM( SUBSTITUTE( SUBSTITUTE( _xlfn.TEXTAFTER(AE6, ":"), """", "" ), ",", "" ) ) -> 00006 | AH6: =AF6 -> TNFCLK | AI6: =AG6 -> 00006
A7: "SLFCLK": "00006", | B7: =TRIM( SUBSTITUTE( SUBSTITUTE( LEFT(A7, FIND(":", A7) - 1), """", "" ), ",", "" ) ) -> SLFCLK | C7: =TRIM( SUBSTITUTE( SUBSTITUTE( _xlfn.TEXTAFTER(A7, ":"), """", "" ), ",", "" ) ) -> 00006 | D7: =B7 -> SLFCLK | E7: =C7 -> 00006 | G7: "SLFCLK": "00006", | H7: =TRIM( SUBSTITUTE( SUBSTITUTE( LEFT(G7, FIND(":", G7) - 1), """", "" ), ",", "" ) ) -> SLFCLK | I7: =TRIM( SUBSTITUTE( SUBSTITUTE( _xlfn.TEXTAFTER(G7, ":"), """", "" ), ",", "" ) ) -> 00006 | J7: =H7 -> SLFCLK | K7: =I7 -> 00006 | M7: "SLFCLK": "00006", | N7: =TRIM( SUBSTITUTE( SUBSTITUTE( LEFT(M7, FIND(":", M7) - 1), """", "" ), ",", "" ) ) -> SLFCLK | O7: =TRIM( SUBSTITUTE( SUBSTITUTE( _xlfn.TEXTAFTER(M7, ":"), """", "" ), ",", "" ) ) -> 00006 | P7: =N7 -> SLFCLK | Q7: =O7 -> 00006 | S7: "SLFCLK": "00006", | T7: =TRIM( SUBSTITUTE( SUBSTITUTE( LEFT(S7, FIND(":", S7) - 1), """", "" ), ",", "" ) ) -> SLFCLK | U7: =TRIM( SUBSTITUTE( SUBSTITUTE( _xlfn.TEXTAFTER(S7, ":"), """", "" ), ",", "" ) ) -> 00006 | V7: =T7 -> SLFCLK | W7: =U7 -> 00006 | Y7: "SLFCLK": "00006", | Z7: =TRIM( SUBSTITUTE( SUBSTITUTE( LEFT(Y7, FIND(":", Y7) - 1), """", "" ), ",", "" ) ) -> SLFCLK | AA7: =TRIM( SUBSTITUTE( SUBSTITUTE( _xlfn.TEXTAFTER(Y7, ":"), """", "" ), ",", "" ) ) -> 00006 | AB7: =Z7 -> SLFCLK | AC7: =AA7 -> 00006 | AE7: "TNFREG": "006", | AF7: =TRIM( SUBSTITUTE( SUBSTITUTE( LEFT(AE7, FIND(":", AE7) - 1), """", "" ), ",", "" ) ) -> TNFREG | AG7: =TRIM( SUBSTITUTE( SUBSTITUTE( _xlfn.TEXTAFTER(AE7, ":"), """", "" ), ",", "" ) ) -> 006 | AH7: =AF7 -> TNFREG | AI7: =AG7 -> 006
A8: "SLFREG": "006", | B8: =TRIM( SUBSTITUTE( SUBSTITUTE( LEFT(A8, FIND(":", A8) - 1), """", "" ), ",", "" ) ) -> SLFREG | C8: =TRIM( SUBSTITUTE( SUBSTITUTE( _xlfn.TEXTAFTER(A8, ":"), """", "" ), ",", "" ) ) -> 006 | D8: =B8 -> SLFREG | E8: =C8 -> 006 | G8: "SLFREG": "006", | H8: =TRIM( SUBSTITUTE( SUBSTITUTE( LEFT(G8, FIND(":", G8) - 1), """", "" ), ",", "" ) ) -> SLFREG | I8: =TRIM( SUBSTITUTE( SUBSTITUTE( _xlfn.TEXTAFTER(G8, ":"), """", "" ), ",", "" ) ) -> 006 | J8: =H8 -> SLFREG | K8: =I8 -> 006 | M8: "SLFREG": "006", | N8: =TRIM( SUBSTITUTE( SUBSTITUTE( LEFT(M8, FIND(":", M8) - 1), """", "" ), ",", "" ) ) -> SLFREG | O8: =TRIM( SUBSTITUTE( SUBSTITUTE( _xlfn.TEXTAFTER(M8, ":"), """", "" ), ",", "" ) ) -> 006 | P8: =N8 -> SLFREG | Q8: =O8 -> 006 | S8: "SLFREG": "006", | T8: =TRIM( SUBSTITUTE( SUBSTITUTE( LEFT(S8, FIND(":", S8) - 1), """", "" ), ",", "" ) ) -> SLFREG | U8: =TRIM( SUBSTITUTE( SUBSTITUTE( _xlfn.TEXTAFTER(S8, ":"), """", "" ), ",", "" ) ) -> 006 | V8: =T8 -> SLFREG | W8: =U8 -> 006 | Y8: "SLFREG": "006", | Z8: =TRIM( SUBSTITUTE( SUBSTITUTE( LEFT(Y8, FIND(":", Y8) - 1), """", "" ), ",", "" ) ) -> SLFREG | AA8: =TRIM( SUBSTITUTE( SUBSTITUTE( _xlfn.TEXTAFTER(Y8, ":"), """", "" ), ",", "" ) ) -> 006 | AB8: =Z8 -> SLFREG | AC8: =AA8 -> 006 | AE8: "TNFTTX": "00539", | AF8: =TRIM( SUBSTITUTE( SUBSTITUTE( LEFT(AE8, FIND(":", AE8) - 1), """", "" ), ",", "" ) ) -> TNFTTX | AG8: =TRIM( SUBSTITUTE( SUBSTITUTE( _xlfn.TEXTAFTER(AE8, ":"), """", "" ), ",", "" ) ) -> 00539 | AH8: =AF8 -> TNFTTX | AI8: =AG8 -> 00539
A9: "SLFTTX": "00539", | B9: =TRIM( SUBSTITUTE( SUBSTITUTE( LEFT(A9, FIND(":", A9) - 1), """", "" ), ",", "" ) ) -> SLFTTX | C9: =TRIM( SUBSTITUTE( SUBSTITUTE( _xlfn.TEXTAFTER(A9, ":"), """", "" ), ",", "" ) ) -> 00539 | D9: =B9 -> SLFTTX | E9: =C9 -> 00539 | G9: "SLFTTX": "00539", | H9: =TRIM( SUBSTITUTE( SUBSTITUTE( LEFT(G9, FIND(":", G9) - 1), """", "" ), ",", "" ) ) -> SLFTTX | I9: =TRIM( SUBSTITUTE( SUBSTITUTE( _xlfn.TEXTAFTER(G9, ":"), """", "" ), ",", "" ) ) -> 00539 | J9: =H9 -> SLFTTX | K9: =I9 -> 00539 | M9: "SLFTTX": "00539", | N9: =TRIM( SUBSTITUTE( SUBSTITUTE( LEFT(M9, FIND(":", M9) - 1), """", "" ), ",", "" ) ) -> SLFTTX | O9: =TRIM( SUBSTITUTE( SUBSTITUTE( _xlfn.TEXTAFTER(M9, ":"), """", "" ), ",", "" ) ) -> 00539 | P9: =N9 -> SLFTTX | Q9: =O9 -> 00539 | S9: "SLFTTX": "00539", | T9: =TRIM( SUBSTITUTE( SUBSTITUTE( LEFT(S9, FIND(":", S9) - 1), """", "" ), ",", "" ) ) -> SLFTTX | U9: =TRIM( SUBSTITUTE( SUBSTITUTE( _xlfn.TEXTAFTER(S9, ":"), """", "" ), ",", "" ) ) -> 00539 | V9: =T9 -> SLFTTX | W9: =U9 -> 00539 | Y9: "SLFTTX": "00539", | Z9: =TRIM( SUBSTITUTE( SUBSTITUTE( LEFT(Y9, FIND(":", Y9) - 1), """", "" ), ",", "" ) ) -> SLFTTX | AA9: =TRIM( SUBSTITUTE( SUBSTITUTE( _xlfn.TEXTAFTER(Y9, ":"), """", "" ), ",", "" ) ) -> 00539 | AB9: =Z9 -> SLFTTX | AC9: =AA9 -> 00539 | AE9: "TNFTSQ": "00006", | AF9: =TRIM( SUBSTITUTE( SUBSTITUTE( LEFT(AE9, FIND(":", AE9) - 1), """", "" ), ",", "" ) ) -> TNFTSQ | AG9: =TRIM( SUBSTITUTE( SUBSTITUTE( _xlfn.TEXTAFTER(AE9, ":"), """", "" ), ",", "" ) ) -> 00006 | AH9: =AF9 -> TNFTSQ | AI9: =AG9 -> 00006
A10: "SLFTSQ": "00001", | B10: =TRIM( SUBSTITUTE( SUBSTITUTE( LEFT(A10, FIND(":", A10) - 1), """", "" ), ",", "" ) ) -> SLFTSQ | C10: =TRIM( SUBSTITUTE( SUBSTITUTE( _xlfn.TEXTAFTER(A10, ":"), """", "" ), ",", "" ) ) -> 00001 | D10: =B10 -> SLFTSQ | E10: =C10 -> 00001 | G10: "SLFTSQ": "00002", | H10: =TRIM( SUBSTITUTE( SUBSTITUTE( LEFT(G10, FIND(":", G10) - 1), """", "" ), ",", "" ) ) -> SLFTSQ | I10: =TRIM( SUBSTITUTE( SUBSTITUTE( _xlfn.TEXTAFTER(G10, ":"), """", "" ), ",", "" ) ) -> 00002 | J10: =H10 -> SLFTSQ | K10: =I10 -> 00002 | M10: "SLFTSQ": "00003", | N10: =TRIM( SUBSTITUTE( SUBSTITUTE( LEFT(M10, FIND(":", M10) - 1), """", "" ), ",", "" ) ) -> SLFTSQ | O10: =TRIM( SUBSTITUTE( SUBSTITUTE( _xlfn.TEXTAFTER(M10, ":"), """", "" ), ",", "" ) ) -> 00003 | P10: =N10 -> SLFTSQ | Q10: =O10 -> 00003 | S10: "SLFTSQ": "00004", | T10: =TRIM( SUBSTITUTE( SUBSTITUTE( LEFT(S10, FIND(":", S10) - 1), """", "" ), ",", "" ) ) -> SLFTSQ | U10: =TRIM( SUBSTITUTE( SUBSTITUTE( _xlfn.TEXTAFTER(S10, ":"), """", "" ), ",", "" ) ) -> 00004 | V10: =T10 -> SLFTSQ | W10: =U10 -> 00004 | Y10: "SLFTSQ": "00005", | Z10: =TRIM( SUBSTITUTE( SUBSTITUTE( LEFT(Y10, FIND(":", Y10) - 1), """", "" ), ",", "" ) ) -> SLFTSQ | AA10: =TRIM( SUBSTITUTE( SUBSTITUTE( _xlfn.TEXTAFTER(Y10, ":"), """", "" ), ",", "" ) ) -> 00005 | AB10: =Z10 -> SLFTSQ | AC10: =AA10 -> 00005 | AE10: "TNFFCD": "DC", | AF10: =TRIM( SUBSTITUTE( SUBSTITUTE( LEFT(AE10, FIND(":", AE10) - 1), """", "" ), ",", "" ) ) -> TNFFCD | AG10: =TRIM( SUBSTITUTE( SUBSTITUTE( _xlfn.TEXTAFTER(AE10, ":"), """", "" ), ",", "" ) ) -> DC | AH10: =AF10 -> TNFFCD | AI10: =AG10 -> DC
A11: "SLFSKU": "000301286", | B11: =TRIM( SUBSTITUTE( SUBSTITUTE( LEFT(A11, FIND(":", A11) - 1), """", "" ), ",", "" ) ) -> SLFSKU | C11: =TRIM( SUBSTITUTE( SUBSTITUTE( _xlfn.TEXTAFTER(A11, ":"), """", "" ), ",", "" ) ) -> 000301286 | D11: =B11 -> SLFSKU | E11: =C11 -> 000301286 | G11: "SLFSKU": "000334898", | H11: =TRIM( SUBSTITUTE( SUBSTITUTE( LEFT(G11, FIND(":", G11) - 1), """", "" ), ",", "" ) ) -> SLFSKU | I11: =TRIM( SUBSTITUTE( SUBSTITUTE( _xlfn.TEXTAFTER(G11, ":"), """", "" ), ",", "" ) ) -> 000334898 | J11: =H11 -> SLFSKU | K11: =I11 -> 000334898 | M11: "SLFSKU": "000050481", | N11: =TRIM( SUBSTITUTE( SUBSTITUTE( LEFT(M11, FIND(":", M11) - 1), """", "" ), ",", "" ) ) -> SLFSKU | O11: =TRIM( SUBSTITUTE( SUBSTITUTE( _xlfn.TEXTAFTER(M11, ":"), """", "" ), ",", "" ) ) -> 000050481 | P11: =N11 -> SLFSKU | Q11: =O11 -> 000050481 | S11: "SLFSKU": "000491309", | T11: =TRIM( SUBSTITUTE( SUBSTITUTE( LEFT(S11, FIND(":", S11) - 1), """", "" ), ",", "" ) ) -> SLFSKU | U11: =TRIM( SUBSTITUTE( SUBSTITUTE( _xlfn.TEXTAFTER(S11, ":"), """", "" ), ",", "" ) ) -> 000491309 | V11: =T11 -> SLFSKU | W11: =U11 -> 000491309 | Y11: "SLFSKU": "000000000", | Z11: =TRIM( SUBSTITUTE( SUBSTITUTE( LEFT(Y11, FIND(":", Y11) - 1), """", "" ), ",", "" ) ) -> SLFSKU | AA11: =TRIM( SUBSTITUTE( SUBSTITUTE( _xlfn.TEXTAFTER(Y11, ":"), """", "" ), ",", "" ) ) -> 000000000 | AB11: =Z11 -> SLFSKU | AC11: =AA11 -> 000000000 | AE11: "TNFAMT": "00000002912", | AF11: =TRIM( SUBSTITUTE( SUBSTITUTE( LEFT(AE11, FIND(":", AE11) - 1), """", "" ), ",", "" ) ) -> TNFAMT | AG11: =TRIM( SUBSTITUTE( SUBSTITUTE( _xlfn.TEXTAFTER(AE11, ":"), """", "" ), ",", "" ) ) -> 00000002912 | AH11: =AF11 -> TNFAMT | AI11: =AG11 -> 00000002912
A12: "SLFQTY": "000000100", | B12: =TRIM( SUBSTITUTE( SUBSTITUTE( LEFT(A12, FIND(":", A12) - 1), """", "" ), ",", "" ) ) -> SLFQTY | C12: =TRIM( SUBSTITUTE( SUBSTITUTE( _xlfn.TEXTAFTER(A12, ":"), """", "" ), ",", "" ) ) -> 000000100 | D12: =B12 -> SLFQTY | E12: =C12 -> 000000100 | G12: "SLFQTY": "000000100", | H12: =TRIM( SUBSTITUTE( SUBSTITUTE( LEFT(G12, FIND(":", G12) - 1), """", "" ), ",", "" ) ) -> SLFQTY | I12: =TRIM( SUBSTITUTE( SUBSTITUTE( _xlfn.TEXTAFTER(G12, ":"), """", "" ), ",", "" ) ) -> 000000100 | J12: =H12 -> SLFQTY | K12: =I12 -> 000000100 | M12: "SLFQTY": "000000100", | N12: =TRIM( SUBSTITUTE( SUBSTITUTE( LEFT(M12, FIND(":", M12) - 1), """", "" ), ",", "" ) ) -> SLFQTY | O12: =TRIM( SUBSTITUTE( SUBSTITUTE( _xlfn.TEXTAFTER(M12, ":"), """", "" ), ",", "" ) ) -> 000000100 | P12: =N12 -> SLFQTY | Q12: =O12 -> 000000100 | S12: "SLFQTY": "000000100", | T12: =TRIM( SUBSTITUTE( SUBSTITUTE( LEFT(S12, FIND(":", S12) - 1), """", "" ), ",", "" ) ) -> SLFQTY | U12: =TRIM( SUBSTITUTE( SUBSTITUTE( _xlfn.TEXTAFTER(S12, ":"), """", "" ), ",", "" ) ) -> 000000100 | V12: =T12 -> SLFQTY | W12: =U12 -> 000000100 | Y12: "SLFQTY": "000000100", | Z12: =TRIM( SUBSTITUTE( SUBSTITUTE( LEFT(Y12, FIND(":", Y12) - 1), """", "" ), ",", "" ) ) -> SLFQTY | AA12: =TRIM( SUBSTITUTE( SUBSTITUTE( _xlfn.TEXTAFTER(Y12, ":"), """", "" ), ",", "" ) ) -> 000000100 | AB12: =Z12 -> SLFQTY | AC12: =AA12 -> 000000100 | AE12: "TNFAMN": "", | AF12: =TRIM( SUBSTITUTE( SUBSTITUTE( LEFT(AE12, FIND(":", AE12) - 1), """", "" ), ",", "" ) ) -> TNFAMN | AG12: =TRIM( SUBSTITUTE( SUBSTITUTE( _xlfn.TEXTAFTER(AE12, ":"), """", "" ), ",", "" ) ) | AH12: =AF12 -> TNFAMN | AI12: =AG12
A13: "SLFQTN": "", | B13: =TRIM( SUBSTITUTE( SUBSTITUTE( LEFT(A13, FIND(":", A13) - 1), """", "" ), ",", "" ) ) -> SLFQTN | C13: =TRIM( SUBSTITUTE( SUBSTITUTE( _xlfn.TEXTAFTER(A13, ":"), """", "" ), ",", "" ) ) | D13: =B13 -> SLFQTN | E13: =C13 | G13: "SLFQTN": "", | H13: =TRIM( SUBSTITUTE( SUBSTITUTE( LEFT(G13, FIND(":", G13) - 1), """", "" ), ",", "" ) ) -> SLFQTN | I13: =TRIM( SUBSTITUTE( SUBSTITUTE( _xlfn.TEXTAFTER(G13, ":"), """", "" ), ",", "" ) ) | J13: =H13 -> SLFQTN | K13: =I13 | M13: "SLFQTN": "", | N13: =TRIM( SUBSTITUTE( SUBSTITUTE( LEFT(M13, FIND(":", M13) - 1), """", "" ), ",", "" ) ) -> SLFQTN | O13: =TRIM( SUBSTITUTE( SUBSTITUTE( _xlfn.TEXTAFTER(M13, ":"), """", "" ), ",", "" ) ) | P13: =N13 -> SLFQTN | Q13: =O13 | S13: "SLFQTN": "", | T13: =TRIM( SUBSTITUTE( SUBSTITUTE( LEFT(S13, FIND(":", S13) - 1), """", "" ), ",", "" ) ) -> SLFQTN | U13: =TRIM( SUBSTITUTE( SUBSTITUTE( _xlfn.TEXTAFTER(S13, ":"), """", "" ), ",", "" ) ) | V13: =T13 -> SLFQTN | W13: =U13 | Y13: "SLFQTN": "", | Z13: =TRIM( SUBSTITUTE( SUBSTITUTE( LEFT(Y13, FIND(":", Y13) - 1), """", "" ), ",", "" ) ) -> SLFQTN | AA13: =TRIM( SUBSTITUTE( SUBSTITUTE( _xlfn.TEXTAFTER(Y13, ":"), """", "" ), ",", "" ) ) | AB13: =Z13 -> SLFQTN | AC13: =AA13 | AE13: "TNFCCD": "***************8644", | AF13: =TRIM( SUBSTITUTE( SUBSTITUTE( LEFT(AE13, FIND(":", AE13) - 1), """", "" ), ",", "" ) ) -> TNFCCD | AG13: =TRIM( SUBSTITUTE( SUBSTITUTE( _xlfn.TEXTAFTER(AE13, ":"), """", "" ), ",", "" ) ) -> ***************8644 | AH13: =AF13 -> TNFCCD | AI13: =AG13 -> ***************8644
A14: "SLFORG": "000000659", | B14: =TRIM( SUBSTITUTE( SUBSTITUTE( LEFT(A14, FIND(":", A14) - 1), """", "" ), ",", "" ) ) -> SLFORG | C14: =TRIM( SUBSTITUTE( SUBSTITUTE( _xlfn.TEXTAFTER(A14, ":"), """", "" ), ",", "" ) ) -> 000000659 | D14: =B14 -> SLFORG | E14: =C14 -> 000000659 | G14: "SLFORG": "000001129", | H14: =TRIM( SUBSTITUTE( SUBSTITUTE( LEFT(G14, FIND(":", G14) - 1), """", "" ), ",", "" ) ) -> SLFORG | I14: =TRIM( SUBSTITUTE( SUBSTITUTE( _xlfn.TEXTAFTER(G14, ":"), """", "" ), ",", "" ) ) -> 000001129 | J14: =H14 -> SLFORG | K14: =I14 -> 000001129 | M14: "SLFORG": "000000399", | N14: =TRIM( SUBSTITUTE( SUBSTITUTE( LEFT(M14, FIND(":", M14) - 1), """", "" ), ",", "" ) ) -> SLFORG | O14: =TRIM( SUBSTITUTE( SUBSTITUTE( _xlfn.TEXTAFTER(M14, ":"), """", "" ), ",", "" ) ) -> 000000399 | P14: =N14 -> SLFORG | Q14: =O14 -> 000000399 | S14: "SLFORG": "000000389", | T14: =TRIM( SUBSTITUTE( SUBSTITUTE( LEFT(S14, FIND(":", S14) - 1), """", "" ), ",", "" ) ) -> SLFORG | U14: =TRIM( SUBSTITUTE( SUBSTITUTE( _xlfn.TEXTAFTER(S14, ":"), """", "" ), ",", "" ) ) -> 000000389 | V14: =T14 -> SLFORG | W14: =U14 -> 000000389 | Y14: "SLFORG": "000000000", | Z14: =TRIM( SUBSTITUTE( SUBSTITUTE( LEFT(Y14, FIND(":", Y14) - 1), """", "" ), ",", "" ) ) -> SLFORG | AA14: =TRIM( SUBSTITUTE( SUBSTITUTE( _xlfn.TEXTAFTER(Y14, ":"), """", "" ), ",", "" ) ) -> 000000000 | AB14: =Z14 -> SLFORG | AC14: =AA14 -> 000000000 | AE14: "TNFEXP": "0000", | AF14: =TRIM( SUBSTITUTE( SUBSTITUTE( LEFT(AE14, FIND(":", AE14) - 1), """", "" ), ",", "" ) ) -> TNFEXP | AG14: =TRIM( SUBSTITUTE( SUBSTITUTE( _xlfn.TEXTAFTER(AE14, ":"), """", "" ), ",", "" ) ) -> 0000 | AH14: =AF14 -> TNFEXP | AI14: =AG14 -> 0000
... A36: "SLFSTS": " ", | B36: =TRIM( SUBSTITUTE( SUBSTITUTE( LEFT(A36, FIND(":", A36) - 1), """", "" ), ",", "" ) ) -> SLFSTS | C36: =TRIM( SUBSTITUTE( SUBSTITUTE( _xlfn.TEXTAFTER(A36, ":"), """", "" ), ",", "" ) ) | D36: =B36 -> SLFSTS | E36: =C36 | G36: "SLFSTS": " ", | H36: =TRIM( SUBSTITUTE( SUBSTITUTE( LEFT(G36, FIND(":", G36) - 1), """", "" ), ",", "" ) ) -> SLFSTS | I36: =TRIM( SUBSTITUTE( SUBSTITUTE( _xlfn.TEXTAFTER(G36, ":"), """", "" ), ",", "" ) ) | J36: =H36 -> SLFSTS | K36: =I36 | M36: "SLFSTS": " ", | N36: =TRIM( SUBSTITUTE( SUBSTITUTE( LEFT(M36, FIND(":", M36) - 1), """", "" ), ",", "" ) ) -> SLFSTS | O36: =TRIM( SUBSTITUTE( SUBSTITUTE( _xlfn.TEXTAFTER(M36, ":"), """", "" ), ",", "" ) ) | P36: =N36 -> SLFSTS | Q36: =O36 | S36: "SLFSTS": " ", | T36: =TRIM( SUBSTITUTE( SUBSTITUTE( LEFT(S36, FIND(":", S36) - 1), """", "" ), ",", "" ) ) -> SLFSTS | U36: =TRIM( SUBSTITUTE( SUBSTITUTE( _xlfn.TEXTAFTER(S36, ":"), """", "" ), ",", "" ) ) | V36: =T36 -> SLFSTS | W36: =U36 | Y36: "SLFSTS": " ", | Z36: =TRIM( SUBSTITUTE( SUBSTITUTE( LEFT(Y36, FIND(":", Y36) - 1), """", "" ), ",", "" ) ) -> SLFSTS | AA36: =TRIM( SUBSTITUTE( SUBSTITUTE( _xlfn.TEXTAFTER(Y36, ":"), """", "" ), ",", "" ) ) | AB36: =Z36 -> SLFSTS | AC36: =AA36 | AE36: "ATFPRO": "" | AF36: =TRIM( SUBSTITUTE( SUBSTITUTE( LEFT(AE36, FIND(":", AE36) - 1), """", "" ), ",", "" ) ) -> ATFPRO | AG36: =TRIM( SUBSTITUTE( SUBSTITUTE( _xlfn.TEXTAFTER(AE36, ":"), """", "" ), ",", "" ) ) | AH36: =AF36 -> ATFPRO | AI36: =AG36
A37: "SLFZIP": "", | B37: =TRIM( SUBSTITUTE( SUBSTITUTE( LEFT(A37, FIND(":", A37) - 1), """", "" ), ",", "" ) ) -> SLFZIP | C37: =TRIM( SUBSTITUTE( SUBSTITUTE( _xlfn.TEXTAFTER(A37, ":"), """", "" ), ",", "" ) ) | D37: =B37 -> SLFZIP | E37: =C37 | G37: "SLFZIP": "", | H37: =TRIM( SUBSTITUTE( SUBSTITUTE( LEFT(G37, FIND(":", G37) - 1), """", "" ), ",", "" ) ) -> SLFZIP | I37: =TRIM( SUBSTITUTE( SUBSTITUTE( _xlfn.TEXTAFTER(G37, ":"), """", "" ), ",", "" ) ) | J37: =H37 -> SLFZIP | K37: =I37 | M37: "SLFZIP": "", | N37: =TRIM( SUBSTITUTE( SUBSTITUTE( LEFT(M37, FIND(":", M37) - 1), """", "" ), ",", "" ) ) -> SLFZIP | O37: =TRIM( SUBSTITUTE( SUBSTITUTE( _xlfn.TEXTAFTER(M37, ":"), """", "" ), ",", "" ) ) | P37: =N37 -> SLFZIP | Q37: =O37 | S37: "SLFZIP": "", | T37: =TRIM( SUBSTITUTE( SUBSTITUTE( LEFT(S37, FIND(":", S37) - 1), """", "" ), ",", "" ) ) -> SLFZIP | U37: =TRIM( SUBSTITUTE( SUBSTITUTE( _xlfn.TEXTAFTER(S37, ":"), """", "" ), ",", "" ) ) | V37: =T37 -> SLFZIP | W37: =U37 | Y37: "SLFZIP": "", | Z37: =TRIM( SUBSTITUTE( SUBSTITUTE( LEFT(Y37, FIND(":", Y37) - 1), """", "" ), ",", "" ) ) -> SLFZIP | AA37: =TRIM( SUBSTITUTE( SUBSTITUTE( _xlfn.TEXTAFTER(Y37, ":"), """", "" ), ",", "" ) ) | AB37: =Z37 -> SLFZIP | AC37: =AA37
A38: "SLFCNM": "", | B38: =TRIM( SUBSTITUTE( SUBSTITUTE( LEFT(A38, FIND(":", A38) - 1), """", "" ), ",", "" ) ) -> SLFCNM | C38: =TRIM( SUBSTITUTE( SUBSTITUTE( _xlfn.TEXTAFTER(A38, ":"), """", "" ), ",", "" ) ) | D38: =B38 -> SLFCNM | E38: =C38 | G38: "SLFCNM": "", | H38: =TRIM( SUBSTITUTE( SUBSTITUTE( LEFT(G38, FIND(":", G38) - 1), """", "" ), ",", "" ) ) -> SLFCNM | I38: =TRIM( SUBSTITUTE( SUBSTITUTE( _xlfn.TEXTAFTER(G38, ":"), """", "" ), ",", "" ) ) | J38: =H38 -> SLFCNM | K38: =I38 | M38: "SLFCNM": "", | N38: =TRIM( SUBSTITUTE( SUBSTITUTE( LEFT(M38, FIND(":", M38) - 1), """", "" ), ",", "" ) ) -> SLFCNM | O38: =TRIM( SUBSTITUTE( SUBSTITUTE( _xlfn.TEXTAFTER(M38, ":"), """", "" ), ",", "" ) ) | P38: =N38 -> SLFCNM | Q38: =O38 | S38: "SLFCNM": "", | T38: =TRIM( SUBSTITUTE( SUBSTITUTE( LEFT(S38, FIND(":", S38) - 1), """", "" ), ",", "" ) ) -> SLFCNM | U38: =TRIM( SUBSTITUTE( SUBSTITUTE( _xlfn.TEXTAFTER(S38, ":"), """", "" ), ",", "" ) ) | V38: =T38 -> SLFCNM | W38: =U38 | Y38: "SLFCNM": "", | Z38: =TRIM( SUBSTITUTE( SUBSTITUTE( LEFT(Y38, FIND(":", Y38) - 1), """", "" ), ",", "" ) ) -> SLFCNM | AA38: =TRIM( SUBSTITUTE( SUBSTITUTE( _xlfn.TEXTAFTER(Y38, ":"), """", "" ), ",", "" ) ) | AB38: =Z38 -> SLFCNM | AC38: =AA38
A39: "SLFNUM": "", | B39: =TRIM( SUBSTITUTE( SUBSTITUTE( LEFT(A39, FIND(":", A39) - 1), """", "" ), ",", "" ) ) -> SLFNUM | C39: =TRIM( SUBSTITUTE( SUBSTITUTE( _xlfn.TEXTAFTER(A39, ":"), """", "" ), ",", "" ) ) | D39: =B39 -> SLFNUM | E39: =C39 | G39: "SLFNUM": "", | H39: =TRIM( SUBSTITUTE( SUBSTITUTE( LEFT(G39, FIND(":", G39) - 1), """", "" ), ",", "" ) ) -> SLFNUM | I39: =TRIM( SUBSTITUTE( SUBSTITUTE( _xlfn.TEXTAFTER(G39, ":"), """", "" ), ",", "" ) ) | J39: =H39 -> SLFNUM | K39: =I39 | M39: "SLFNUM": "", | N39: =TRIM( SUBSTITUTE( SUBSTITUTE( LEFT(M39, FIND(":", M39) - 1), """", "" ), ",", "" ) ) -> SLFNUM | O39: =TRIM( SUBSTITUTE( SUBSTITUTE( _xlfn.TEXTAFTER(M39, ":"), """", "" ), ",", "" ) ) | P39: =N39 -> SLFNUM | Q39: =O39 | S39: "SLFNUM": "", | T39: =TRIM( SUBSTITUTE( SUBSTITUTE( LEFT(S39, FIND(":", S39) - 1), """", "" ), ",", "" ) ) -> SLFNUM | U39: =TRIM( SUBSTITUTE( SUBSTITUTE( _xlfn.TEXTAFTER(S39, ":"), """", "" ), ",", "" ) ) | V39: =T39 -> SLFNUM | W39: =U39 | Y39: "SLFNUM": "", | Z39: =TRIM( SUBSTITUTE( SUBSTITUTE( LEFT(Y39, FIND(":", Y39) - 1), """", "" ), ",", "" ) ) -> SLFNUM | AA39: =TRIM( SUBSTITUTE( SUBSTITUTE( _xlfn.TEXTAFTER(Y39, ":"), """", "" ), ",", "" ) ) | AB39: =Z39 -> SLFNUM | AC39: =AA39
A40: "SLFRSN": "", | B40: =TRIM( SUBSTITUTE( SUBSTITUTE( LEFT(A40, FIND(":", A40) - 1), """", "" ), ",", "" ) ) -> SLFRSN | C40: =TRIM( SUBSTITUTE( SUBSTITUTE( _xlfn.TEXTAFTER(A40, ":"), """", "" ), ",", "" ) ) | D40: =B40 -> SLFRSN | E40: =C40 | G40: "SLFRSN": "", | H40: =TRIM( SUBSTITUTE( SUBSTITUTE( LEFT(G40, FIND(":", G40) - 1), """", "" ), ",", "" ) ) -> SLFRSN | I40: =TRIM( SUBSTITUTE( SUBSTITUTE( _xlfn.TEXTAFTER(G40, ":"), """", "" ), ",", "" ) ) | J40: =H40 -> SLFRSN | K40: =I40 | M40: "SLFRSN": "", | N40: =TRIM( SUBSTITUTE( SUBSTITUTE( LEFT(M40, FIND(":", M40) - 1), """", "" ), ",", "" ) ) -> SLFRSN | O40: =TRIM( SUBSTITUTE( SUBSTITUTE( _xlfn.TEXTAFTER(M40, ":"), """", "" ), ",", "" ) ) | P40: =N40 -> SLFRSN | Q40: =O40 | S40: "SLFRSN": "", | T40: =TRIM( SUBSTITUTE( SUBSTITUTE( LEFT(S40, FIND(":", S40) - 1), """", "" ), ",", "" ) ) -> SLFRSN | U40: =TRIM( SUBSTITUTE( SUBSTITUTE( _xlfn.TEXTAFTER(S40, ":"), """", "" ), ",", "" ) ) | V40: =T40 -> SLFRSN | W40: =U40 | Y40: "SLFRSN": "", | Z40: =TRIM( SUBSTITUTE( SUBSTITUTE( LEFT(Y40, FIND(":", Y40) - 1), """", "" ), ",", "" ) ) -> SLFRSN | AA40: =TRIM( SUBSTITUTE( SUBSTITUTE( _xlfn.TEXTAFTER(Y40, ":"), """", "" ), ",", "" ) ) | AB40: =Z40 -> SLFRSN | AC40: =AA40
A41: "SLFOSP": "00000", | B41: =TRIM( SUBSTITUTE( SUBSTITUTE( LEFT(A41, FIND(":", A41) - 1), """", "" ), ",", "" ) ) -> SLFOSP | C41: =TRIM( SUBSTITUTE( SUBSTITUTE( _xlfn.TEXTAFTER(A41, ":"), """", "" ), ",", "" ) ) -> 00000 | D41: =B41 -> SLFOSP | E41: =C41 -> 00000 | G41: "SLFOSP": "00000", | H41: =TRIM( SUBSTITUTE( SUBSTITUTE( LEFT(G41, FIND(":", G41) - 1), """", "" ), ",", "" ) ) -> SLFOSP | I41: =TRIM( SUBSTITUTE( SUBSTITUTE( _xlfn.TEXTAFTER(G41, ":"), """", "" ), ",", "" ) ) -> 00000 | J41: =H41 -> SLFOSP | K41: =I41 -> 00000 | M41: "SLFOSP": "00000", | N41: =TRIM( SUBSTITUTE( SUBSTITUTE( LEFT(M41, FIND(":", M41) - 1), """", "" ), ",", "" ) ) -> SLFOSP | O41: =TRIM( SUBSTITUTE( SUBSTITUTE( _xlfn.TEXTAFTER(M41, ":"), """", "" ), ",", "" ) ) -> 00000 | P41: =N41 -> SLFOSP | Q41: =O41 -> 00000 | S41: "SLFOSP": "00000", | T41: =TRIM( SUBSTITUTE( SUBSTITUTE( LEFT(S41, FIND(":", S41) - 1), """", "" ), ",", "" ) ) -> SLFOSP | U41: =TRIM( SUBSTITUTE( SUBSTITUTE( _xlfn.TEXTAFTER(S41, ":"), """", "" ), ",", "" ) ) -> 00000 | V41: =T41 -> SLFOSP | W41: =U41 -> 00000 | Y41: "SLFOSP": "00000", | Z41: =TRIM( SUBSTITUTE( SUBSTITUTE( LEFT(Y41, FIND(":", Y41) - 1), """", "" ), ",", "" ) ) -> SLFOSP | AA41: =TRIM( SUBSTITUTE( SUBSTITUTE( _xlfn.TEXTAFTER(Y41, ":"), """", "" ), ",", "" ) ) -> 00000 | AB41: =Z41 -> SLFOSP | AC41: =AA41 -> 00000
A42: "SLFOST": "00000", | B42: =TRIM( SUBSTITUTE( SUBSTITUTE( LEFT(A42, FIND(":", A42) - 1), """", "" ), ",", "" ) ) -> SLFOST | C42: =TRIM( SUBSTITUTE( SUBSTITUTE( _xlfn.TEXTAFTER(A42, ":"), """", "" ), ",", "" ) ) -> 00000 | D42: =B42 -> SLFOST | E42: =C42 -> 00000 | G42: "SLFOST": "00000", | H42: =TRIM( SUBSTITUTE( SUBSTITUTE( LEFT(G42, FIND(":", G42) - 1), """", "" ), ",", "" ) ) -> SLFOST | I42: =TRIM( SUBSTITUTE( SUBSTITUTE( _xlfn.TEXTAFTER(G42, ":"), """", "" ), ",", "" ) ) -> 00000 | J42: =H42 -> SLFOST | K42: =I42 -> 00000 | M42: "SLFOST": "00000", | N42: =TRIM( SUBSTITUTE( SUBSTITUTE( LEFT(M42, FIND(":", M42) - 1), """", "" ), ",", "" ) ) -> SLFOST | O42: =TRIM( SUBSTITUTE( SUBSTITUTE( _xlfn.TEXTAFTER(M42, ":"), """", "" ), ",", "" ) ) -> 00000 | P42: =N42 -> SLFOST | Q42: =O42 -> 00000 | S42: "SLFOST": "00000", | T42: =TRIM( SUBSTITUTE( SUBSTITUTE( LEFT(S42, FIND(":", S42) - 1), """", "" ), ",", "" ) ) -> SLFOST | U42: =TRIM( SUBSTITUTE( SUBSTITUTE( _xlfn.TEXTAFTER(S42, ":"), """", "" ), ",", "" ) ) -> 00000 | V42: =T42 -> SLFOST | W42: =U42 -> 00000 | Y42: "SLFOST": "00000", | Z42: =TRIM( SUBSTITUTE( SUBSTITUTE( LEFT(Y42, FIND(":", Y42) - 1), """", "" ), ",", "" ) ) -> SLFOST | AA42: =TRIM( SUBSTITUTE( SUBSTITUTE( _xlfn.TEXTAFTER(Y42, ":"), """", "" ), ",", "" ) ) -> 00000 | AB42: =Z42 -> SLFOST | AC42: =AA42 -> 00000
A43: "SLFGDA": "000000000", | B43: =TRIM( SUBSTITUTE( SUBSTITUTE( LEFT(A43, FIND(":", A43) - 1), """", "" ), ",", "" ) ) -> SLFGDA | C43: =TRIM( SUBSTITUTE( SUBSTITUTE( _xlfn.TEXTAFTER(A43, ":"), """", "" ), ",", "" ) ) -> 000000000 | D43: =B43 -> SLFGDA | E43: =C43 -> 000000000 | G43: "SLFGDA": "000000000", | H43: =TRIM( SUBSTITUTE( SUBSTITUTE( LEFT(G43, FIND(":", G43) - 1), """", "" ), ",", "" ) ) -> SLFGDA | I43: =TRIM( SUBSTITUTE( SUBSTITUTE( _xlfn.TEXTAFTER(G43, ":"), """", "" ), ",", "" ) ) -> 000000000 | J43: =H43 -> SLFGDA | K43: =I43 -> 000000000 | M43: "SLFGDA": "000000000", | N43: =TRIM( SUBSTITUTE( SUBSTITUTE( LEFT(M43, FIND(":", M43) - 1), """", "" ), ",", "" ) ) -> SLFGDA | O43: =TRIM( SUBSTITUTE( SUBSTITUTE( _xlfn.TEXTAFTER(M43, ":"), """", "" ), ",", "" ) ) -> 000000000 | P43: =N43 -> SLFGDA | Q43: =O43 -> 000000000 | S43: "SLFGDA": "000000000", | T43: =TRIM( SUBSTITUTE( SUBSTITUTE( LEFT(S43, FIND(":", S43) - 1), """", "" ), ",", "" ) ) -> SLFGDA | U43: =TRIM( SUBSTITUTE( SUBSTITUTE( _xlfn.TEXTAFTER(S43, ":"), """", "" ), ",", "" ) ) -> 000000000 | V43: =T43 -> SLFGDA | W43: =U43 -> 000000000 | Y43: "SLFGDA": "000000000", | Z43: =TRIM( SUBSTITUTE( SUBSTITUTE( LEFT(Y43, FIND(":", Y43) - 1), """", "" ), ",", "" ) ) -> SLFGDA | AA43: =TRIM( SUBSTITUTE( SUBSTITUTE( _xlfn.TEXTAFTER(Y43, ":"), """", "" ), ",", "" ) ) -> 000000000 | AB43: =Z43 -> SLFGDA | AC43: =AA43 -> 000000000
A44: "SLFGDS": "", | B44: =TRIM( SUBSTITUTE( SUBSTITUTE( LEFT(A44, FIND(":", A44) - 1), """", "" ), ",", "" ) ) -> SLFGDS | C44: =TRIM( SUBSTITUTE( SUBSTITUTE( _xlfn.TEXTAFTER(A44, ":"), """", "" ), ",", "" ) ) | D44: =B44 -> SLFGDS | E44: =C44 | G44: "SLFGDS": "", | H44: =TRIM( SUBSTITUTE( SUBSTITUTE( LEFT(G44, FIND(":", G44) - 1), """", "" ), ",", "" ) ) -> SLFGDS | I44: =TRIM( SUBSTITUTE( SUBSTITUTE( _xlfn.TEXTAFTER(G44, ":"), """", "" ), ",", "" ) ) | J44: =H44 -> SLFGDS | K44: =I44 | M44: "SLFGDS": "", | N44: =TRIM( SUBSTITUTE( SUBSTITUTE( LEFT(M44, FIND(":", M44) - 1), """", "" ), ",", "" ) ) -> SLFGDS | O44: =TRIM( SUBSTITUTE( SUBSTITUTE( _xlfn.TEXTAFTER(M44, ":"), """", "" ), ",", "" ) ) | P44: =N44 -> SLFGDS | Q44: =O44 | S44: "SLFGDS": "", | T44: =TRIM( SUBSTITUTE( SUBSTITUTE( LEFT(S44, FIND(":", S44) - 1), """", "" ), ",", "" ) ) -> SLFGDS | U44: =TRIM( SUBSTITUTE( SUBSTITUTE( _xlfn.TEXTAFTER(S44, ":"), """", "" ), ",", "" ) ) | V44: =T44 -> SLFGDS | W44: =U44 | Y44: "SLFGDS": "", | Z44: =TRIM( SUBSTITUTE( SUBSTITUTE( LEFT(Y44, FIND(":", Y44) - 1), """", "" ), ",", "" ) ) -> SLFGDS | AA44: =TRIM( SUBSTITUTE( SUBSTITUTE( _xlfn.TEXTAFTER(Y44, ":"), """", "" ), ",", "" ) ) | AB44: =Z44 -> SLFGDS | AC44: =AA44
A45: "SLFGDR": "00", | B45: =TRIM( SUBSTITUTE( SUBSTITUTE( LEFT(A45, FIND(":", A45) - 1), """", "" ), ",", "" ) ) -> SLFGDR | C45: =TRIM( SUBSTITUTE( SUBSTITUTE( _xlfn.TEXTAFTER(A45, ":"), """", "" ), ",", "" ) ) -> 00 | D45: =B45 -> SLFGDR | E45: =C45 -> 00 | G45: "SLFGDR": "00", | H45: =TRIM( SUBSTITUTE( SUBSTITUTE( LEFT(G45, FIND(":", G45) - 1), """", "" ), ",", "" ) ) -> SLFGDR | I45: =TRIM( SUBSTITUTE( SUBSTITUTE( _xlfn.TEXTAFTER(G45, ":"), """", "" ), ",", "" ) ) -> 00 | J45: =H45 -> SLFGDR | K45: =I45 -> 00 | M45: "SLFGDR": "00", | N45: =TRIM( SUBSTITUTE( SUBSTITUTE( LEFT(M45, FIND(":", M45) - 1), """", "" ), ",", "" ) ) -> SLFGDR | O45: =TRIM( SUBSTITUTE( SUBSTITUTE( _xlfn.TEXTAFTER(M45, ":"), """", "" ), ",", "" ) ) -> 00 | P45: =N45 -> SLFGDR | Q45: =O45 -> 00 | S45: "SLFGDR": "00", | T45: =TRIM( SUBSTITUTE( SUBSTITUTE( LEFT(S45, FIND(":", S45) - 1), """", "" ), ",", "" ) ) -> SLFGDR | U45: =TRIM( SUBSTITUTE( SUBSTITUTE( _xlfn.TEXTAFTER(S45, ":"), """", "" ), ",", "" ) ) -> 00 | V45: =T45 -> SLFGDR | W45: =U45 -> 00 | Y45: "SLFGDR": "00", | Z45: =TRIM( SUBSTITUTE( SUBSTITUTE( LEFT(Y45, FIND(":", Y45) - 1), """", "" ), ",", "" ) ) -> SLFGDR | AA45: =TRIM( SUBSTITUTE( SUBSTITUTE( _xlfn.TEXTAFTER(Y45, ":"), """", "" ), ",", "" ) ) -> 00 | AB45: =Z45 -> SLFGDR | AC45: =AA45 -> 00
A46: "SLFRDR": "00", | B46: =TRIM( SUBSTITUTE( SUBSTITUTE( LEFT(A46, FIND(":", A46) - 1), """", "" ), ",", "" ) ) -> SLFRDR | C46: =TRIM( SUBSTITUTE( SUBSTITUTE( _xlfn.TEXTAFTER(A46, ":"), """", "" ), ",", "" ) ) -> 00 | D46: =B46 -> SLFRDR | E46: =C46 -> 00 | G46: "SLFRDR": "00", | H46: =TRIM( SUBSTITUTE( SUBSTITUTE( LEFT(G46, FIND(":", G46) - 1), """", "" ), ",", "" ) ) -> SLFRDR | I46: =TRIM( SUBSTITUTE( SUBSTITUTE( _xlfn.TEXTAFTER(G46, ":"), """", "" ), ",", "" ) ) -> 00 | J46: =H46 -> SLFRDR | K46: =I46 -> 00 | M46: "SLFRDR": "00", | N46: =TRIM( SUBSTITUTE( SUBSTITUTE( LEFT(M46, FIND(":", M46) - 1), """", "" ), ",", "" ) ) -> SLFRDR | O46: =TRIM( SUBSTITUTE( SUBSTITUTE( _xlfn.TEXTAFTER(M46, ":"), """", "" ), ",", "" ) ) -> 00 | P46: =N46 -> SLFRDR | Q46: =O46 -> 00 | S46: "SLFRDR": "00", | T46: =TRIM( SUBSTITUTE( SUBSTITUTE( LEFT(S46, FIND(":", S46) - 1), """", "" ), ",", "" ) ) -> SLFRDR | U46: =TRIM( SUBSTITUTE( SUBSTITUTE( _xlfn.TEXTAFTER(S46, ":"), """", "" ), ",", "" ) ) -> 00 | V46: =T46 -> SLFRDR | W46: =U46 -> 00 | Y46: "SLFRDR": "00", | Z46: =TRIM( SUBSTITUTE( SUBSTITUTE( LEFT(Y46, FIND(":", Y46) - 1), """", "" ), ",", "" ) ) -> SLFRDR | AA46: =TRIM( SUBSTITUTE( SUBSTITUTE( _xlfn.TEXTAFTER(Y46, ":"), """", "" ), ",", "" ) ) -> 00 | AB46: =Z46 -> SLFRDR | AC46: =AA46 -> 00
A47: "SLFSCN": "N", | B47: =TRIM( SUBSTITUTE( SUBSTITUTE( LEFT(A47, FIND(":", A47) - 1), """", "" ), ",", "" ) ) -> SLFSCN | C47: =TRIM( SUBSTITUTE( SUBSTITUTE( _xlfn.TEXTAFTER(A47, ":"), """", "" ), ",", "" ) ) -> N | D47: =B47 -> SLFSCN | E47: =C47 -> N | G47: "SLFSCN": "Y", | H47: =TRIM( SUBSTITUTE( SUBSTITUTE( LEFT(G47, FIND(":", G47) - 1), """", "" ), ",", "" ) ) -> SLFSCN | I47: =TRIM( SUBSTITUTE( SUBSTITUTE( _xlfn.TEXTAFTER(G47, ":"), """", "" ), ",", "" ) ) -> Y | J47: =H47 -> SLFSCN | K47: =I47 -> Y | M47: "SLFSCN": "Y", | N47: =TRIM( SUBSTITUTE( SUBSTITUTE( LEFT(M47, FIND(":", M47) - 1), """", "" ), ",", "" ) ) -> SLFSCN | O47: =TRIM( SUBSTITUTE( SUBSTITUTE( _xlfn.TEXTAFTER(M47, ":"), """", "" ), ",", "" ) ) -> Y | P47: =N47 -> SLFSCN | Q47: =O47 -> Y | S47: "SLFSCN": "Y", | T47: =TRIM( SUBSTITUTE( SUBSTITUTE( LEFT(S47, FIND(":", S47) - 1), """", "" ), ",", "" ) ) -> SLFSCN | U47: =TRIM( SUBSTITUTE( SUBSTITUTE( _xlfn.TEXTAFTER(S47, ":"), """", "" ), ",", "" ) ) -> Y | V47: =T47 -> SLFSCN | W47: =U47 -> Y | Y47: "SLFSCN": "N", | Z47: =TRIM( SUBSTITUTE( SUBSTITUTE( LEFT(Y47, FIND(":", Y47) - 1), """", "" ), ",", "" ) ) -> SLFSCN | AA47: =TRIM( SUBSTITUTE( SUBSTITUTE( _xlfn.TEXTAFTER(Y47, ":"), """", "" ), ",", "" ) ) -> N | AB47: =Z47 -> SLFSCN | AC47: =AA47 -> N
A48: "SLFACD": "ON ", | B48: =TRIM( SUBSTITUTE( SUBSTITUTE( LEFT(A48, FIND(":", A48) - 1), """", "" ), ",", "" ) ) -> SLFACD | C48: =TRIM( SUBSTITUTE( SUBSTITUTE( _xlfn.TEXTAFTER(A48, ":"), """", "" ), ",", "" ) ) -> ON | D48: =B48 -> SLFACD | E48: =C48 -> ON | G48: "SLFACD": "ON ", | H48: =TRIM( SUBSTITUTE( SUBSTITUTE( LEFT(G48, FIND(":", G48) - 1), """", "" ), ",", "" ) ) -> SLFACD | I48: =TRIM( SUBSTITUTE( SUBSTITUTE( _xlfn.TEXTAFTER(G48, ":"), """", "" ), ",", "" ) ) -> ON | J48: =H48 -> SLFACD | K48: =I48 -> ON | M48: "SLFACD": "ON ", | N48: =TRIM( SUBSTITUTE( SUBSTITUTE( LEFT(M48, FIND(":", M48) - 1), """", "" ), ",", "" ) ) -> SLFACD | O48: =TRIM( SUBSTITUTE( SUBSTITUTE( _xlfn.TEXTAFTER(M48, ":"), """", "" ), ",", "" ) ) -> ON | P48: =N48 -> SLFACD | Q48: =O48 -> ON | S48: "SLFACD": "ON ", | T48: =TRIM( SUBSTITUTE( SUBSTITUTE( LEFT(S48, FIND(":", S48) - 1), """", "" ), ",", "" ) ) -> SLFACD | U48: =TRIM( SUBSTITUTE( SUBSTITUTE( _xlfn.TEXTAFTER(S48, ":"), """", "" ), ",", "" ) ) -> ON | V48: =T48 -> SLFACD | W48: =U48 -> ON | Y48: "SLFACD": "HON ", | Z48: =TRIM( SUBSTITUTE( SUBSTITUTE( LEFT(Y48, FIND(":", Y48) - 1), """", "" ), ",", "" ) ) -> SLFACD | AA48: =TRIM( SUBSTITUTE( SUBSTITUTE( _xlfn.TEXTAFTER(Y48, ":"), """", "" ), ",", "" ) ) -> HON | AB48: =Z48 -> SLFACD | AC48: =AA48 -> HON
... A71: "SLFEML": "", | B71: =TRIM( SUBSTITUTE( SUBSTITUTE( LEFT(A71, FIND(":", A71) - 1), """", "" ), ",", "" ) ) -> SLFEML | C71: =TRIM( SUBSTITUTE( SUBSTITUTE( _xlfn.TEXTAFTER(A71, ":"), """", "" ), ",", "" ) ) | D71: =B71 -> SLFEML | E71: =C71 | G71: "SLFEML": "", | H71: =TRIM( SUBSTITUTE( SUBSTITUTE( LEFT(G71, FIND(":", G71) - 1), """", "" ), ",", "" ) ) -> SLFEML | I71: =TRIM( SUBSTITUTE( SUBSTITUTE( _xlfn.TEXTAFTER(G71, ":"), """", "" ), ",", "" ) ) | J71: =H71 -> SLFEML | K71: =I71 | M71: "SLFEML": "", | N71: =TRIM( SUBSTITUTE( SUBSTITUTE( LEFT(M71, FIND(":", M71) - 1), """", "" ), ",", "" ) ) -> SLFEML | O71: =TRIM( SUBSTITUTE( SUBSTITUTE( _xlfn.TEXTAFTER(M71, ":"), """", "" ), ",", "" ) ) | P71: =N71 -> SLFEML | Q71: =O71 | S71: "SLFEML": "", | T71: =TRIM( SUBSTITUTE( SUBSTITUTE( LEFT(S71, FIND(":", S71) - 1), """", "" ), ",", "" ) ) -> SLFEML | U71: =TRIM( SUBSTITUTE( SUBSTITUTE( _xlfn.TEXTAFTER(S71, ":"), """", "" ), ",", "" ) ) | V71: =T71 -> SLFEML | W71: =U71 | Y71: "SLFECN": 0 | Z71: =TRIM( SUBSTITUTE( SUBSTITUTE( LEFT(Y71, FIND(":", Y71) - 1), """", "" ), ",", "" ) ) -> SLFECN | AA71: =TRIM( SUBSTITUTE( SUBSTITUTE( _xlfn.TEXTAFTER(Y71, ":"), """", "" ), ",", "" ) ) -> 0 | AB71: =Z71 -> SLFECN | AC71: =AA71 -> 0
A72: "SLFECN": 0 | B72: =TRIM( SUBSTITUTE( SUBSTITUTE( LEFT(A72, FIND(":", A72) - 1), """", "" ), ",", "" ) ) -> SLFECN | C72: =TRIM( SUBSTITUTE( SUBSTITUTE( _xlfn.TEXTAFTER(A72, ":"), """", "" ), ",", "" ) ) -> 0 | D72: =B72 -> SLFECN | E72: =C72 -> 0 | G72: "SLFECN": 0 | H72: =TRIM( SUBSTITUTE( SUBSTITUTE( LEFT(G72, FIND(":", G72) - 1), """", "" ), ",", "" ) ) -> SLFECN | I72: =TRIM( SUBSTITUTE( SUBSTITUTE( _xlfn.TEXTAFTER(G72, ":"), """", "" ), ",", "" ) ) -> 0 | J72: =H72 -> SLFECN | K72: =I72 -> 0 | M72: "SLFECN": 0 | N72: =TRIM( SUBSTITUTE( SUBSTITUTE( LEFT(M72, FIND(":", M72) - 1), """", "" ), ",", "" ) ) -> SLFECN | O72: =TRIM( SUBSTITUTE( SUBSTITUTE( _xlfn.TEXTAFTER(M72, ":"), """", "" ), ",", "" ) ) -> 0 | P72: =N72 -> SLFECN | Q72: =O72 -> 0 | S72: "SLFECN": 0 | T72: =TRIM( SUBSTITUTE( SUBSTITUTE( LEFT(S72, FIND(":", S72) - 1), """", "" ), ",", "" ) ) -> SLFECN | U72: =TRIM( SUBSTITUTE( SUBSTITUTE( _xlfn.TEXTAFTER(S72, ":"), """", "" ), ",", "" ) ) -> 0 | V72: =T72 -> SLFECN | W72: =U72 -> 0

Sheet Sheet3
A1: SKU LIne | G1: Tax LIne | M1: SKU2 | S1: Tender
A2: SLFTTP: "01", | B2: =TRIM( SUBSTITUTE( SUBSTITUTE( LEFT(A2, FIND(":", A2) - 1), """", "" ), ",", "" ) ) -> SLFTTP | C2: =TRIM( SUBSTITUTE( SUBSTITUTE( _xlfn.TEXTAFTER(A2, ":"), """", "" ), ",", "" ) ) -> 01 | D2: =B2 -> SLFTTP | E2: =C2 -> 01 | G2: "SLFTTP": "01", | H2: =TRIM( SUBSTITUTE( SUBSTITUTE( LEFT(G2, FIND(":", G2) - 1), """", "" ), ",", "" ) ) -> SLFTTP | I2: =TRIM( SUBSTITUTE( SUBSTITUTE( _xlfn.TEXTAFTER(G2, ":"), """", "" ), ",", "" ) ) -> 01 | J2: =H2 -> SLFTTP | K2: =I2 -> 01 | M2: "SLFTTP": "01", | N2: =TRIM( SUBSTITUTE( SUBSTITUTE( LEFT(M2, FIND(":", M2) - 1), """", "" ), ",", "" ) ) -> SLFTTP | O2: =TRIM( SUBSTITUTE( SUBSTITUTE( _xlfn.TEXTAFTER(M2, ":"), """", "" ), ",", "" ) ) -> 01 | P2: =N2 -> SLFTTP | Q2: =O2 -> 01 | S2: TNFTTP: "01", | T2: =TRIM( SUBSTITUTE( SUBSTITUTE( LEFT(S2, FIND(":", S2) - 1), """", "" ), ",", "" ) ) -> TNFTTP | U2: =TRIM( SUBSTITUTE( SUBSTITUTE( _xlfn.TEXTAFTER(S2, ":"), """", "" ), ",", "" ) ) -> 01 | V2: =T2 -> TNFTTP | W2: =U2 -> 01
A3: "SLFLNT": "01", | B3: =TRIM( SUBSTITUTE( SUBSTITUTE( LEFT(A3, FIND(":", A3) - 1), """", "" ), ",", "" ) ) -> SLFLNT | C3: =TRIM( SUBSTITUTE( SUBSTITUTE( _xlfn.TEXTAFTER(A3, ":"), """", "" ), ",", "" ) ) -> 01 | D3: =B3 -> SLFLNT | E3: =C3 -> 01 | G3: "SLFLNT": "XH", | H3: =TRIM( SUBSTITUTE( SUBSTITUTE( LEFT(G3, FIND(":", G3) - 1), """", "" ), ",", "" ) ) -> SLFLNT | I3: =TRIM( SUBSTITUTE( SUBSTITUTE( _xlfn.TEXTAFTER(G3, ":"), """", "" ), ",", "" ) ) -> XH | J3: =H3 -> SLFLNT | K3: =I3 -> XH | M3: "SLFLNT": "01", | N3: =TRIM( SUBSTITUTE( SUBSTITUTE( LEFT(M3, FIND(":", M3) - 1), """", "" ), ",", "" ) ) -> SLFLNT | O3: =TRIM( SUBSTITUTE( SUBSTITUTE( _xlfn.TEXTAFTER(M3, ":"), """", "" ), ",", "" ) ) -> 01 | P3: =N3 -> SLFLNT | Q3: =O3 -> 01 | S3: "TNFTDT": "260128", | T3: =TRIM( SUBSTITUTE( SUBSTITUTE( LEFT(S3, FIND(":", S3) - 1), """", "" ), ",", "" ) ) -> TNFTDT | U3: =TRIM( SUBSTITUTE( SUBSTITUTE( _xlfn.TEXTAFTER(S3, ":"), """", "" ), ",", "" ) ) -> 260128 | V3: =T3 -> TNFTDT | W3: =U3 -> 260128
A4: "SLFTDT": "260128", | B4: =TRIM( SUBSTITUTE( SUBSTITUTE( LEFT(A4, FIND(":", A4) - 1), """", "" ), ",", "" ) ) -> SLFTDT | C4: =TRIM( SUBSTITUTE( SUBSTITUTE( _xlfn.TEXTAFTER(A4, ":"), """", "" ), ",", "" ) ) -> 260128 | D4: =B4 -> SLFTDT | E4: =C4 -> 260128 | G4: "SLFTDT": "260128", | H4: =TRIM( SUBSTITUTE( SUBSTITUTE( LEFT(G4, FIND(":", G4) - 1), """", "" ), ",", "" ) ) -> SLFTDT | I4: =TRIM( SUBSTITUTE( SUBSTITUTE( _xlfn.TEXTAFTER(G4, ":"), """", "" ), ",", "" ) ) -> 260128 | J4: =H4 -> SLFTDT | K4: =I4 -> 260128 | M4: "SLFTDT": "260128", | N4: =TRIM( SUBSTITUTE( SUBSTITUTE( LEFT(M4, FIND(":", M4) - 1), """", "" ), ",", "" ) ) -> SLFTDT | O4: =TRIM( SUBSTITUTE( SUBSTITUTE( _xlfn.TEXTAFTER(M4, ":"), """", "" ), ",", "" ) ) -> 260128 | P4: =N4 -> SLFTDT | Q4: =O4 -> 260128 | S4: "TNFTTM": "144416", | T4: =TRIM( SUBSTITUTE( SUBSTITUTE( LEFT(S4, FIND(":", S4) - 1), """", "" ), ",", "" ) ) -> TNFTTM | U4: =TRIM( SUBSTITUTE( SUBSTITUTE( _xlfn.TEXTAFTER(S4, ":"), """", "" ), ",", "" ) ) -> 144416 | V4: =T4 -> TNFTTM | W4: =U4 -> 144416
A5: "SLFTTM": "144416", | B5: =TRIM( SUBSTITUTE( SUBSTITUTE( LEFT(A5, FIND(":", A5) - 1), """", "" ), ",", "" ) ) -> SLFTTM | C5: =TRIM( SUBSTITUTE( SUBSTITUTE( _xlfn.TEXTAFTER(A5, ":"), """", "" ), ",", "" ) ) -> 144416 | D5: =B5 -> SLFTTM | E5: =C5 -> 144416 | G5: "SLFTTM": "144416", | H5: =TRIM( SUBSTITUTE( SUBSTITUTE( LEFT(G5, FIND(":", G5) - 1), """", "" ), ",", "" ) ) -> SLFTTM | I5: =TRIM( SUBSTITUTE( SUBSTITUTE( _xlfn.TEXTAFTER(G5, ":"), """", "" ), ",", "" ) ) -> 144416 | J5: =H5 -> SLFTTM | K5: =I5 -> 144416 | M5: "SLFTTM": "144416", | N5: =TRIM( SUBSTITUTE( SUBSTITUTE( LEFT(M5, FIND(":", M5) - 1), """", "" ), ",", "" ) ) -> SLFTTM | O5: =TRIM( SUBSTITUTE( SUBSTITUTE( _xlfn.TEXTAFTER(M5, ":"), """", "" ), ",", "" ) ) -> 144416 | P5: =N5 -> SLFTTM | Q5: =O5 -> 144416 | S5: "TNFCLK": "00085", | T5: =TRIM( SUBSTITUTE( SUBSTITUTE( LEFT(S5, FIND(":", S5) - 1), """", "" ), ",", "" ) ) -> TNFCLK | U5: =TRIM( SUBSTITUTE( SUBSTITUTE( _xlfn.TEXTAFTER(S5, ":"), """", "" ), ",", "" ) ) -> 00085 | V5: =T5 -> TNFCLK | W5: =U5 -> 00085
A6: "SLFCLK": "00085", | B6: =TRIM( SUBSTITUTE( SUBSTITUTE( LEFT(A6, FIND(":", A6) - 1), """", "" ), ",", "" ) ) -> SLFCLK | C6: =TRIM( SUBSTITUTE( SUBSTITUTE( _xlfn.TEXTAFTER(A6, ":"), """", "" ), ",", "" ) ) -> 00085 | D6: =B6 -> SLFCLK | E6: =C6 -> 00085 | G6: "SLFCLK": "00085", | H6: =TRIM( SUBSTITUTE( SUBSTITUTE( LEFT(G6, FIND(":", G6) - 1), """", "" ), ",", "" ) ) -> SLFCLK | I6: =TRIM( SUBSTITUTE( SUBSTITUTE( _xlfn.TEXTAFTER(G6, ":"), """", "" ), ",", "" ) ) -> 00085 | J6: =H6 -> SLFCLK | K6: =I6 -> 00085 | M6: "SLFCLK": "00085", | N6: =TRIM( SUBSTITUTE( SUBSTITUTE( LEFT(M6, FIND(":", M6) - 1), """", "" ), ",", "" ) ) -> SLFCLK | O6: =TRIM( SUBSTITUTE( SUBSTITUTE( _xlfn.TEXTAFTER(M6, ":"), """", "" ), ",", "" ) ) -> 00085 | P6: =N6 -> SLFCLK | Q6: =O6 -> 00085 | S6: "TNFREG": "085", | T6: =TRIM( SUBSTITUTE( SUBSTITUTE( LEFT(S6, FIND(":", S6) - 1), """", "" ), ",", "" ) ) -> TNFREG | U6: =TRIM( SUBSTITUTE( SUBSTITUTE( _xlfn.TEXTAFTER(S6, ":"), """", "" ), ",", "" ) ) -> 085 | V6: =T6 -> TNFREG | W6: =U6 -> 085
A7: "SLFREG": "085", | B7: =TRIM( SUBSTITUTE( SUBSTITUTE( LEFT(A7, FIND(":", A7) - 1), """", "" ), ",", "" ) ) -> SLFREG | C7: =TRIM( SUBSTITUTE( SUBSTITUTE( _xlfn.TEXTAFTER(A7, ":"), """", "" ), ",", "" ) ) -> 085 | D7: =B7 -> SLFREG | E7: =C7 -> 085 | G7: "SLFREG": "085", | H7: =TRIM( SUBSTITUTE( SUBSTITUTE( LEFT(G7, FIND(":", G7) - 1), """", "" ), ",", "" ) ) -> SLFREG | I7: =TRIM( SUBSTITUTE( SUBSTITUTE( _xlfn.TEXTAFTER(G7, ":"), """", "" ), ",", "" ) ) -> 085 | J7: =H7 -> SLFREG | K7: =I7 -> 085 | M7: "SLFREG": "085", | N7: =TRIM( SUBSTITUTE( SUBSTITUTE( LEFT(M7, FIND(":", M7) - 1), """", "" ), ",", "" ) ) -> SLFREG | O7: =TRIM( SUBSTITUTE( SUBSTITUTE( _xlfn.TEXTAFTER(M7, ":"), """", "" ), ",", "" ) ) -> 085 | P7: =N7 -> SLFREG | Q7: =O7 -> 085 | S7: "TNFTTX": "00604", | T7: =TRIM( SUBSTITUTE( SUBSTITUTE( LEFT(S7, FIND(":", S7) - 1), """", "" ), ",", "" ) ) -> TNFTTX | U7: =TRIM( SUBSTITUTE( SUBSTITUTE( _xlfn.TEXTAFTER(S7, ":"), """", "" ), ",", "" ) ) -> 00604 | V7: =T7 -> TNFTTX | W7: =U7 -> 00604
A8: "SLFTTX": "00604", | B8: =TRIM( SUBSTITUTE( SUBSTITUTE( LEFT(A8, FIND(":", A8) - 1), """", "" ), ",", "" ) ) -> SLFTTX | C8: =TRIM( SUBSTITUTE( SUBSTITUTE( _xlfn.TEXTAFTER(A8, ":"), """", "" ), ",", "" ) ) -> 00604 | D8: =B8 -> SLFTTX | E8: =C8 -> 00604 | G8: "SLFTTX": "00604", | H8: =TRIM( SUBSTITUTE( SUBSTITUTE( LEFT(G8, FIND(":", G8) - 1), """", "" ), ",", "" ) ) -> SLFTTX | I8: =TRIM( SUBSTITUTE( SUBSTITUTE( _xlfn.TEXTAFTER(G8, ":"), """", "" ), ",", "" ) ) -> 00604 | J8: =H8 -> SLFTTX | K8: =I8 -> 00604 | M8: "SLFTTX": "00604", | N8: =TRIM( SUBSTITUTE( SUBSTITUTE( LEFT(M8, FIND(":", M8) - 1), """", "" ), ",", "" ) ) -> SLFTTX | O8: =TRIM( SUBSTITUTE( SUBSTITUTE( _xlfn.TEXTAFTER(M8, ":"), """", "" ), ",", "" ) ) -> 00604 | P8: =N8 -> SLFTTX | Q8: =O8 -> 00604 | S8: "TNFTSQ": "00004", | T8: =TRIM( SUBSTITUTE( SUBSTITUTE( LEFT(S8, FIND(":", S8) - 1), """", "" ), ",", "" ) ) -> TNFTSQ | U8: =TRIM( SUBSTITUTE( SUBSTITUTE( _xlfn.TEXTAFTER(S8, ":"), """", "" ), ",", "" ) ) -> 00004 | V8: =T8 -> TNFTSQ | W8: =U8 -> 00004
A9: "SLFTSQ": "00001", | B9: =TRIM( SUBSTITUTE( SUBSTITUTE( LEFT(A9, FIND(":", A9) - 1), """", "" ), ",", "" ) ) -> SLFTSQ | C9: =TRIM( SUBSTITUTE( SUBSTITUTE( _xlfn.TEXTAFTER(A9, ":"), """", "" ), ",", "" ) ) -> 00001 | D9: =B9 -> SLFTSQ | E9: =C9 -> 00001 | G9: "SLFTSQ": "00003", | H9: =TRIM( SUBSTITUTE( SUBSTITUTE( LEFT(G9, FIND(":", G9) - 1), """", "" ), ",", "" ) ) -> SLFTSQ | I9: =TRIM( SUBSTITUTE( SUBSTITUTE( _xlfn.TEXTAFTER(G9, ":"), """", "" ), ",", "" ) ) -> 00003 | J9: =H9 -> SLFTSQ | K9: =I9 -> 00003 | M9: "SLFTSQ": "00002", | N9: =TRIM( SUBSTITUTE( SUBSTITUTE( LEFT(M9, FIND(":", M9) - 1), """", "" ), ",", "" ) ) -> SLFTSQ | O9: =TRIM( SUBSTITUTE( SUBSTITUTE( _xlfn.TEXTAFTER(M9, ":"), """", "" ), ",", "" ) ) -> 00002 | P9: =N9 -> SLFTSQ | Q9: =O9 -> 00002 | S9: "TNFFCD": "VI", | T9: =TRIM( SUBSTITUTE( SUBSTITUTE( LEFT(S9, FIND(":", S9) - 1), """", "" ), ",", "" ) ) -> TNFFCD | U9: =TRIM( SUBSTITUTE( SUBSTITUTE( _xlfn.TEXTAFTER(S9, ":"), """", "" ), ",", "" ) ) -> VI | V9: =T9 -> TNFFCD | W9: =U9 -> VI
A10: "SLFSKU": "000272093", | B10: =TRIM( SUBSTITUTE( SUBSTITUTE( LEFT(A10, FIND(":", A10) - 1), """", "" ), ",", "" ) ) -> SLFSKU | C10: =TRIM( SUBSTITUTE( SUBSTITUTE( _xlfn.TEXTAFTER(A10, ":"), """", "" ), ",", "" ) ) -> 000272093 | D10: =B10 -> SLFSKU | E10: =C10 -> 000272093 | G10: "SLFSKU": "000000000", | H10: =TRIM( SUBSTITUTE( SUBSTITUTE( LEFT(G10, FIND(":", G10) - 1), """", "" ), ",", "" ) ) -> SLFSKU | I10: =TRIM( SUBSTITUTE( SUBSTITUTE( _xlfn.TEXTAFTER(G10, ":"), """", "" ), ",", "" ) ) -> 000000000 | J10: =H10 -> SLFSKU | K10: =I10 -> 000000000 | M10: "SLFSKU": "000125728", | N10: =TRIM( SUBSTITUTE( SUBSTITUTE( LEFT(M10, FIND(":", M10) - 1), """", "" ), ",", "" ) ) -> SLFSKU | O10: =TRIM( SUBSTITUTE( SUBSTITUTE( _xlfn.TEXTAFTER(M10, ":"), """", "" ), ",", "" ) ) -> 000125728 | P10: =N10 -> SLFSKU | Q10: =O10 -> 000125728 | S10: "TNFAMT": "00000016832", | T10: =TRIM( SUBSTITUTE( SUBSTITUTE( LEFT(S10, FIND(":", S10) - 1), """", "" ), ",", "" ) ) -> TNFAMT | U10: =TRIM( SUBSTITUTE( SUBSTITUTE( _xlfn.TEXTAFTER(S10, ":"), """", "" ), ",", "" ) ) -> 00000016832 | V10: =T10 -> TNFAMT | W10: =U10 -> 00000016832
A11: "SLFQTY": "000001200", | B11: =TRIM( SUBSTITUTE( SUBSTITUTE( LEFT(A11, FIND(":", A11) - 1), """", "" ), ",", "" ) ) -> SLFQTY | C11: =TRIM( SUBSTITUTE( SUBSTITUTE( _xlfn.TEXTAFTER(A11, ":"), """", "" ), ",", "" ) ) -> 000001200 | D11: =B11 -> SLFQTY | E11: =C11 -> 000001200 | G11: "SLFQTY": "000000100", | H11: =TRIM( SUBSTITUTE( SUBSTITUTE( LEFT(G11, FIND(":", G11) - 1), """", "" ), ",", "" ) ) -> SLFQTY | I11: =TRIM( SUBSTITUTE( SUBSTITUTE( _xlfn.TEXTAFTER(G11, ":"), """", "" ), ",", "" ) ) -> 000000100 | J11: =H11 -> SLFQTY | K11: =I11 -> 000000100 | M11: "SLFQTY": "000000100", | N11: =TRIM( SUBSTITUTE( SUBSTITUTE( LEFT(M11, FIND(":", M11) - 1), """", "" ), ",", "" ) ) -> SLFQTY | O11: =TRIM( SUBSTITUTE( SUBSTITUTE( _xlfn.TEXTAFTER(M11, ":"), """", "" ), ",", "" ) ) -> 000000100 | P11: =N11 -> SLFQTY | Q11: =O11 -> 000000100 | S11: "TNFAMN": "", | T11: =TRIM( SUBSTITUTE( SUBSTITUTE( LEFT(S11, FIND(":", S11) - 1), """", "" ), ",", "" ) ) -> TNFAMN | U11: =TRIM( SUBSTITUTE( SUBSTITUTE( _xlfn.TEXTAFTER(S11, ":"), """", "" ), ",", "" ) ) | V11: =T11 -> TNFAMN | W11: =U11
A12: "SLFQTN": "", | B12: =TRIM( SUBSTITUTE( SUBSTITUTE( LEFT(A12, FIND(":", A12) - 1), """", "" ), ",", "" ) ) -> SLFQTN | C12: =TRIM( SUBSTITUTE( SUBSTITUTE( _xlfn.TEXTAFTER(A12, ":"), """", "" ), ",", "" ) ) | D12: =B12 -> SLFQTN | E12: =C12 | G12: "SLFQTN": "", | H12: =TRIM( SUBSTITUTE( SUBSTITUTE( LEFT(G12, FIND(":", G12) - 1), """", "" ), ",", "" ) ) -> SLFQTN | I12: =TRIM( SUBSTITUTE( SUBSTITUTE( _xlfn.TEXTAFTER(G12, ":"), """", "" ), ",", "" ) ) | J12: =H12 -> SLFQTN | K12: =I12 | M12: "SLFQTN": "", | N12: =TRIM( SUBSTITUTE( SUBSTITUTE( LEFT(M12, FIND(":", M12) - 1), """", "" ), ",", "" ) ) -> SLFQTN | O12: =TRIM( SUBSTITUTE( SUBSTITUTE( _xlfn.TEXTAFTER(M12, ":"), """", "" ), ",", "" ) ) | P12: =N12 -> SLFQTN | Q12: =O12 | S12: "TNFCCD": "***************4902", | T12: =TRIM( SUBSTITUTE( SUBSTITUTE( LEFT(S12, FIND(":", S12) - 1), """", "" ), ",", "" ) ) -> TNFCCD | U12: =TRIM( SUBSTITUTE( SUBSTITUTE( _xlfn.TEXTAFTER(S12, ":"), """", "" ), ",", "" ) ) -> ***************4902 | V12: =T12 -> TNFCCD | W12: =U12 -> ***************4902
A13: "SLFORG": "000000083", | B13: =TRIM( SUBSTITUTE( SUBSTITUTE( LEFT(A13, FIND(":", A13) - 1), """", "" ), ",", "" ) ) -> SLFORG | C13: =TRIM( SUBSTITUTE( SUBSTITUTE( _xlfn.TEXTAFTER(A13, ":"), """", "" ), ",", "" ) ) -> 000000083 | D13: =B13 -> SLFORG | E13: =C13 -> 000000083 | G13: "SLFORG": "000000000", | H13: =TRIM( SUBSTITUTE( SUBSTITUTE( LEFT(G13, FIND(":", G13) - 1), """", "" ), ",", "" ) ) -> SLFORG | I13: =TRIM( SUBSTITUTE( SUBSTITUTE( _xlfn.TEXTAFTER(G13, ":"), """", "" ), ",", "" ) ) -> 000000000 | J13: =H13 -> SLFORG | K13: =I13 -> 000000000 | M13: "SLFORG": "000013900", | N13: =TRIM( SUBSTITUTE( SUBSTITUTE( LEFT(M13, FIND(":", M13) - 1), """", "" ), ",", "" ) ) -> SLFORG | O13: =TRIM( SUBSTITUTE( SUBSTITUTE( _xlfn.TEXTAFTER(M13, ":"), """", "" ), ",", "" ) ) -> 000013900 | P13: =N13 -> SLFORG | Q13: =O13 -> 000013900 | S13: "TNFEXP": "0000", | T13: =TRIM( SUBSTITUTE( SUBSTITUTE( LEFT(S13, FIND(":", S13) - 1), """", "" ), ",", "" ) ) -> TNFEXP | U13: =TRIM( SUBSTITUTE( SUBSTITUTE( _xlfn.TEXTAFTER(S13, ":"), """", "" ), ",", "" ) ) -> 0000 | V13: =T13 -> TNFEXP | W13: =U13 -> 0000
... A35: "SLFSTS": " ", | B35: =TRIM( SUBSTITUTE( SUBSTITUTE( LEFT(A35, FIND(":", A35) - 1), """", "" ), ",", "" ) ) -> SLFSTS | C35: =TRIM( SUBSTITUTE( SUBSTITUTE( _xlfn.TEXTAFTER(A35, ":"), """", "" ), ",", "" ) ) | D35: =B35 -> SLFSTS | E35: =C35 | G35: "SLFSTS": " ", | H35: =TRIM( SUBSTITUTE( SUBSTITUTE( LEFT(G35, FIND(":", G35) - 1), """", "" ), ",", "" ) ) -> SLFSTS | I35: =TRIM( SUBSTITUTE( SUBSTITUTE( _xlfn.TEXTAFTER(G35, ":"), """", "" ), ",", "" ) ) | J35: =H35 -> SLFSTS | K35: =I35 | M35: "SLFSTS": " ", | N35: =TRIM( SUBSTITUTE( SUBSTITUTE( LEFT(M35, FIND(":", M35) - 1), """", "" ), ",", "" ) ) -> SLFSTS | O35: =TRIM( SUBSTITUTE( SUBSTITUTE( _xlfn.TEXTAFTER(M35, ":"), """", "" ), ",", "" ) ) | P35: =N35 -> SLFSTS | Q35: =O35 | S35: "ATFPRO": "" | T35: =TRIM( SUBSTITUTE( SUBSTITUTE( LEFT(S35, FIND(":", S35) - 1), """", "" ), ",", "" ) ) -> ATFPRO | U35: =TRIM( SUBSTITUTE( SUBSTITUTE( _xlfn.TEXTAFTER(S35, ":"), """", "" ), ",", "" ) ) | V35: =T35 -> ATFPRO | W35: =U35
A36: "SLFZIP": "", | B36: =TRIM( SUBSTITUTE( SUBSTITUTE( LEFT(A36, FIND(":", A36) - 1), """", "" ), ",", "" ) ) -> SLFZIP | C36: =TRIM( SUBSTITUTE( SUBSTITUTE( _xlfn.TEXTAFTER(A36, ":"), """", "" ), ",", "" ) ) | D36: =B36 -> SLFZIP | E36: =C36 | G36: "SLFZIP": "", | H36: =TRIM( SUBSTITUTE( SUBSTITUTE( LEFT(G36, FIND(":", G36) - 1), """", "" ), ",", "" ) ) -> SLFZIP | I36: =TRIM( SUBSTITUTE( SUBSTITUTE( _xlfn.TEXTAFTER(G36, ":"), """", "" ), ",", "" ) ) | J36: =H36 -> SLFZIP | K36: =I36 | M36: "SLFZIP": "", | N36: =TRIM( SUBSTITUTE( SUBSTITUTE( LEFT(M36, FIND(":", M36) - 1), """", "" ), ",", "" ) ) -> SLFZIP | O36: =TRIM( SUBSTITUTE( SUBSTITUTE( _xlfn.TEXTAFTER(M36, ":"), """", "" ), ",", "" ) ) | P36: =N36 -> SLFZIP | Q36: =O36
A37: "SLFCNM": "", | B37: =TRIM( SUBSTITUTE( SUBSTITUTE( LEFT(A37, FIND(":", A37) - 1), """", "" ), ",", "" ) ) -> SLFCNM | C37: =TRIM( SUBSTITUTE( SUBSTITUTE( _xlfn.TEXTAFTER(A37, ":"), """", "" ), ",", "" ) ) | D37: =B37 -> SLFCNM | E37: =C37 | G37: "SLFCNM": "", | H37: =TRIM( SUBSTITUTE( SUBSTITUTE( LEFT(G37, FIND(":", G37) - 1), """", "" ), ",", "" ) ) -> SLFCNM | I37: =TRIM( SUBSTITUTE( SUBSTITUTE( _xlfn.TEXTAFTER(G37, ":"), """", "" ), ",", "" ) ) | J37: =H37 -> SLFCNM | K37: =I37 | M37: "SLFCNM": "", | N37: =TRIM( SUBSTITUTE( SUBSTITUTE( LEFT(M37, FIND(":", M37) - 1), """", "" ), ",", "" ) ) -> SLFCNM | O37: =TRIM( SUBSTITUTE( SUBSTITUTE( _xlfn.TEXTAFTER(M37, ":"), """", "" ), ",", "" ) ) | P37: =N37 -> SLFCNM | Q37: =O37
A38: "SLFNUM": "", | B38: =TRIM( SUBSTITUTE( SUBSTITUTE( LEFT(A38, FIND(":", A38) - 1), """", "" ), ",", "" ) ) -> SLFNUM | C38: =TRIM( SUBSTITUTE( SUBSTITUTE( _xlfn.TEXTAFTER(A38, ":"), """", "" ), ",", "" ) ) | D38: =B38 -> SLFNUM | E38: =C38 | G38: "SLFNUM": "", | H38: =TRIM( SUBSTITUTE( SUBSTITUTE( LEFT(G38, FIND(":", G38) - 1), """", "" ), ",", "" ) ) -> SLFNUM | I38: =TRIM( SUBSTITUTE( SUBSTITUTE( _xlfn.TEXTAFTER(G38, ":"), """", "" ), ",", "" ) ) | J38: =H38 -> SLFNUM | K38: =I38 | M38: "SLFNUM": "", | N38: =TRIM( SUBSTITUTE( SUBSTITUTE( LEFT(M38, FIND(":", M38) - 1), """", "" ), ",", "" ) ) -> SLFNUM | O38: =TRIM( SUBSTITUTE( SUBSTITUTE( _xlfn.TEXTAFTER(M38, ":"), """", "" ), ",", "" ) ) | P38: =N38 -> SLFNUM | Q38: =O38
A39: "SLFRSN": "", | B39: =TRIM( SUBSTITUTE( SUBSTITUTE( LEFT(A39, FIND(":", A39) - 1), """", "" ), ",", "" ) ) -> SLFRSN | C39: =TRIM( SUBSTITUTE( SUBSTITUTE( _xlfn.TEXTAFTER(A39, ":"), """", "" ), ",", "" ) ) | D39: =B39 -> SLFRSN | E39: =C39 | G39: "SLFRSN": "", | H39: =TRIM( SUBSTITUTE( SUBSTITUTE( LEFT(G39, FIND(":", G39) - 1), """", "" ), ",", "" ) ) -> SLFRSN | I39: =TRIM( SUBSTITUTE( SUBSTITUTE( _xlfn.TEXTAFTER(G39, ":"), """", "" ), ",", "" ) ) | J39: =H39 -> SLFRSN | K39: =I39 | M39: "SLFRSN": "", | N39: =TRIM( SUBSTITUTE( SUBSTITUTE( LEFT(M39, FIND(":", M39) - 1), """", "" ), ",", "" ) ) -> SLFRSN | O39: =TRIM( SUBSTITUTE( SUBSTITUTE( _xlfn.TEXTAFTER(M39, ":"), """", "" ), ",", "" ) ) | P39: =N39 -> SLFRSN | Q39: =O39
A40: "SLFOSP": "00000", | B40: =TRIM( SUBSTITUTE( SUBSTITUTE( LEFT(A40, FIND(":", A40) - 1), """", "" ), ",", "" ) ) -> SLFOSP | C40: =TRIM( SUBSTITUTE( SUBSTITUTE( _xlfn.TEXTAFTER(A40, ":"), """", "" ), ",", "" ) ) -> 00000 | D40: =B40 -> SLFOSP | E40: =C40 -> 00000 | G40: "SLFOSP": "00000", | H40: =TRIM( SUBSTITUTE( SUBSTITUTE( LEFT(G40, FIND(":", G40) - 1), """", "" ), ",", "" ) ) -> SLFOSP | I40: =TRIM( SUBSTITUTE( SUBSTITUTE( _xlfn.TEXTAFTER(G40, ":"), """", "" ), ",", "" ) ) -> 00000 | J40: =H40 -> SLFOSP | K40: =I40 -> 00000 | M40: "SLFOSP": "00000", | N40: =TRIM( SUBSTITUTE( SUBSTITUTE( LEFT(M40, FIND(":", M40) - 1), """", "" ), ",", "" ) ) -> SLFOSP | O40: =TRIM( SUBSTITUTE( SUBSTITUTE( _xlfn.TEXTAFTER(M40, ":"), """", "" ), ",", "" ) ) -> 00000 | P40: =N40 -> SLFOSP | Q40: =O40 -> 00000
A41: "SLFOST": "00000", | B41: =TRIM( SUBSTITUTE( SUBSTITUTE( LEFT(A41, FIND(":", A41) - 1), """", "" ), ",", "" ) ) -> SLFOST | C41: =TRIM( SUBSTITUTE( SUBSTITUTE( _xlfn.TEXTAFTER(A41, ":"), """", "" ), ",", "" ) ) -> 00000 | D41: =B41 -> SLFOST | E41: =C41 -> 00000 | G41: "SLFOST": "00000", | H41: =TRIM( SUBSTITUTE( SUBSTITUTE( LEFT(G41, FIND(":", G41) - 1), """", "" ), ",", "" ) ) -> SLFOST | I41: =TRIM( SUBSTITUTE( SUBSTITUTE( _xlfn.TEXTAFTER(G41, ":"), """", "" ), ",", "" ) ) -> 00000 | J41: =H41 -> SLFOST | K41: =I41 -> 00000 | M41: "SLFOST": "00000", | N41: =TRIM( SUBSTITUTE( SUBSTITUTE( LEFT(M41, FIND(":", M41) - 1), """", "" ), ",", "" ) ) -> SLFOST | O41: =TRIM( SUBSTITUTE( SUBSTITUTE( _xlfn.TEXTAFTER(M41, ":"), """", "" ), ",", "" ) ) -> 00000 | P41: =N41 -> SLFOST | Q41: =O41 -> 00000
A42: "SLFGDA": "000000000", | B42: =TRIM( SUBSTITUTE( SUBSTITUTE( LEFT(A42, FIND(":", A42) - 1), """", "" ), ",", "" ) ) -> SLFGDA | C42: =TRIM( SUBSTITUTE( SUBSTITUTE( _xlfn.TEXTAFTER(A42, ":"), """", "" ), ",", "" ) ) -> 000000000 | D42: =B42 -> SLFGDA | E42: =C42 -> 000000000 | G42: "SLFGDA": "000000000", | H42: =TRIM( SUBSTITUTE( SUBSTITUTE( LEFT(G42, FIND(":", G42) - 1), """", "" ), ",", "" ) ) -> SLFGDA | I42: =TRIM( SUBSTITUTE( SUBSTITUTE( _xlfn.TEXTAFTER(G42, ":"), """", "" ), ",", "" ) ) -> 000000000 | J42: =H42 -> SLFGDA | K42: =I42 -> 000000000 | M42: "SLFGDA": "000000000", | N42: =TRIM( SUBSTITUTE( SUBSTITUTE( LEFT(M42, FIND(":", M42) - 1), """", "" ), ",", "" ) ) -> SLFGDA | O42: =TRIM( SUBSTITUTE( SUBSTITUTE( _xlfn.TEXTAFTER(M42, ":"), """", "" ), ",", "" ) ) -> 000000000 | P42: =N42 -> SLFGDA | Q42: =O42 -> 000000000
A43: "SLFGDS": "", | B43: =TRIM( SUBSTITUTE( SUBSTITUTE( LEFT(A43, FIND(":", A43) - 1), """", "" ), ",", "" ) ) -> SLFGDS | C43: =TRIM( SUBSTITUTE( SUBSTITUTE( _xlfn.TEXTAFTER(A43, ":"), """", "" ), ",", "" ) ) | D43: =B43 -> SLFGDS | E43: =C43 | G43: "SLFGDS": "", | H43: =TRIM( SUBSTITUTE( SUBSTITUTE( LEFT(G43, FIND(":", G43) - 1), """", "" ), ",", "" ) ) -> SLFGDS | I43: =TRIM( SUBSTITUTE( SUBSTITUTE( _xlfn.TEXTAFTER(G43, ":"), """", "" ), ",", "" ) ) | J43: =H43 -> SLFGDS | K43: =I43 | M43: "SLFGDS": "", | N43: =TRIM( SUBSTITUTE( SUBSTITUTE( LEFT(M43, FIND(":", M43) - 1), """", "" ), ",", "" ) ) -> SLFGDS | O43: =TRIM( SUBSTITUTE( SUBSTITUTE( _xlfn.TEXTAFTER(M43, ":"), """", "" ), ",", "" ) ) | P43: =N43 -> SLFGDS | Q43: =O43
A44: "SLFGDR": "00", | B44: =TRIM( SUBSTITUTE( SUBSTITUTE( LEFT(A44, FIND(":", A44) - 1), """", "" ), ",", "" ) ) -> SLFGDR | C44: =TRIM( SUBSTITUTE( SUBSTITUTE( _xlfn.TEXTAFTER(A44, ":"), """", "" ), ",", "" ) ) -> 00 | D44: =B44 -> SLFGDR | E44: =C44 -> 00 | G44: "SLFGDR": "00", | H44: =TRIM( SUBSTITUTE( SUBSTITUTE( LEFT(G44, FIND(":", G44) - 1), """", "" ), ",", "" ) ) -> SLFGDR | I44: =TRIM( SUBSTITUTE( SUBSTITUTE( _xlfn.TEXTAFTER(G44, ":"), """", "" ), ",", "" ) ) -> 00 | J44: =H44 -> SLFGDR | K44: =I44 -> 00 | M44: "SLFGDR": "00", | N44: =TRIM( SUBSTITUTE( SUBSTITUTE( LEFT(M44, FIND(":", M44) - 1), """", "" ), ",", "" ) ) -> SLFGDR | O44: =TRIM( SUBSTITUTE( SUBSTITUTE( _xlfn.TEXTAFTER(M44, ":"), """", "" ), ",", "" ) ) -> 00 | P44: =N44 -> SLFGDR | Q44: =O44 -> 00
A45: "SLFRDR": "00", | B45: =TRIM( SUBSTITUTE( SUBSTITUTE( LEFT(A45, FIND(":", A45) - 1), """", "" ), ",", "" ) ) -> SLFRDR | C45: =TRIM( SUBSTITUTE( SUBSTITUTE( _xlfn.TEXTAFTER(A45, ":"), """", "" ), ",", "" ) ) -> 00 | D45: =B45 -> SLFRDR | E45: =C45 -> 00 | G45: "SLFRDR": "00", | H45: =TRIM( SUBSTITUTE( SUBSTITUTE( LEFT(G45, FIND(":", G45) - 1), """", "" ), ",", "" ) ) -> SLFRDR | I45: =TRIM( SUBSTITUTE( SUBSTITUTE( _xlfn.TEXTAFTER(G45, ":"), """", "" ), ",", "" ) ) -> 00 | J45: =H45 -> SLFRDR | K45: =I45 -> 00 | M45: "SLFRDR": "00", | N45: =TRIM( SUBSTITUTE( SUBSTITUTE( LEFT(M45, FIND(":", M45) - 1), """", "" ), ",", "" ) ) -> SLFRDR | O45: =TRIM( SUBSTITUTE( SUBSTITUTE( _xlfn.TEXTAFTER(M45, ":"), """", "" ), ",", "" ) ) -> 00 | P45: =N45 -> SLFRDR | Q45: =O45 -> 00
A46: "SLFSCN": "N", | B46: =TRIM( SUBSTITUTE( SUBSTITUTE( LEFT(A46, FIND(":", A46) - 1), """", "" ), ",", "" ) ) -> SLFSCN | C46: =TRIM( SUBSTITUTE( SUBSTITUTE( _xlfn.TEXTAFTER(A46, ":"), """", "" ), ",", "" ) ) -> N | D46: =B46 -> SLFSCN | E46: =C46 -> N | G46: "SLFSCN": "N", | H46: =TRIM( SUBSTITUTE( SUBSTITUTE( LEFT(G46, FIND(":", G46) - 1), """", "" ), ",", "" ) ) -> SLFSCN | I46: =TRIM( SUBSTITUTE( SUBSTITUTE( _xlfn.TEXTAFTER(G46, ":"), """", "" ), ",", "" ) ) -> N | J46: =H46 -> SLFSCN | K46: =I46 -> N | M46: "SLFSCN": "N", | N46: =TRIM( SUBSTITUTE( SUBSTITUTE( LEFT(M46, FIND(":", M46) - 1), """", "" ), ",", "" ) ) -> SLFSCN | O46: =TRIM( SUBSTITUTE( SUBSTITUTE( _xlfn.TEXTAFTER(M46, ":"), """", "" ), ",", "" ) ) -> N | P46: =N46 -> SLFSCN | Q46: =O46 -> N
A47: "SLFACD": "ON ", | B47: =TRIM( SUBSTITUTE( SUBSTITUTE( LEFT(A47, FIND(":", A47) - 1), """", "" ), ",", "" ) ) -> SLFACD | C47: =TRIM( SUBSTITUTE( SUBSTITUTE( _xlfn.TEXTAFTER(A47, ":"), """", "" ), ",", "" ) ) -> ON | D47: =B47 -> SLFACD | E47: =C47 -> ON | G47: "SLFACD": "HON ", | H47: =TRIM( SUBSTITUTE( SUBSTITUTE( LEFT(G47, FIND(":", G47) - 1), """", "" ), ",", "" ) ) -> SLFACD | I47: =TRIM( SUBSTITUTE( SUBSTITUTE( _xlfn.TEXTAFTER(G47, ":"), """", "" ), ",", "" ) ) -> HON | J47: =H47 -> SLFACD | K47: =I47 -> HON | M47: "SLFACD": "ON ", | N47: =TRIM( SUBSTITUTE( SUBSTITUTE( LEFT(M47, FIND(":", M47) - 1), """", "" ), ",", "" ) ) -> SLFACD | O47: =TRIM( SUBSTITUTE( SUBSTITUTE( _xlfn.TEXTAFTER(M47, ":"), """", "" ), ",", "" ) ) -> ON | P47: =N47 -> SLFACD | Q47: =O47 -> ON
... A70: "SLFEML": "", | B70: =TRIM( SUBSTITUTE( SUBSTITUTE( LEFT(A70, FIND(":", A70) - 1), """", "" ), ",", "" ) ) -> SLFEML | C70: =TRIM( SUBSTITUTE( SUBSTITUTE( _xlfn.TEXTAFTER(A70, ":"), """", "" ), ",", "" ) ) | D70: =B70 -> SLFEML | E70: =C70 | G70: "SLFEML": "", | H70: =TRIM( SUBSTITUTE( SUBSTITUTE( LEFT(G70, FIND(":", G70) - 1), """", "" ), ",", "" ) ) -> SLFEML | I70: =TRIM( SUBSTITUTE( SUBSTITUTE( _xlfn.TEXTAFTER(G70, ":"), """", "" ), ",", "" ) ) | J70: =H70 -> SLFEML | K70: =I70 | M70: "SLFEML": "", | N70: =TRIM( SUBSTITUTE( SUBSTITUTE( LEFT(M70, FIND(":", M70) - 1), """", "" ), ",", "" ) ) -> SLFEML | O70: =TRIM( SUBSTITUTE( SUBSTITUTE( _xlfn.TEXTAFTER(M70, ":"), """", "" ), ",", "" ) ) | P70: =N70 -> SLFEML | Q70: =O70
A71: "SLFECN": 0 | B71: =TRIM( SUBSTITUTE( SUBSTITUTE( LEFT(A71, FIND(":", A71) - 1), """", "" ), ",", "" ) ) -> SLFECN | C71: =TRIM( SUBSTITUTE( SUBSTITUTE( _xlfn.TEXTAFTER(A71, ":"), """", "" ), ",", "" ) ) -> 0 | D71: =B71 -> SLFECN | E71: =C71 -> 0 | G71: "SLFECN": 0 | M71: "SLFECN": 0 | N71: =TRIM( SUBSTITUTE( SUBSTITUTE( LEFT(M71, FIND(":", M71) - 1), """", "" ), ",", "" ) ) -> SLFECN | O71: =TRIM( SUBSTITUTE( SUBSTITUTE( _xlfn.TEXTAFTER(M71, ":"), """", "" ), ",", "" ) ) -> 0 | P71: =N71 -> SLFECN | Q71: =O71 -> 0
M72: }
